[
  {
    "nom": "Bordeaux",
    "slug": "bordeaux",
    "codeInsee": "33063",
    "codePostal": "33000",
    "population": 267991,
    "latitude": 44.8624,
    "longitude": -0.5848,
    "altitude": 6,
    "logements": 144860,
    "logementsMaison": 12,
    "prixM2Moyen": 4750,
    "vehiculesElectriques": 8130,
    "croissanceVE": 31,
    "bornesPubliques": 229,
    "intercommunalite": "Bordeaux Métropole",
    "canton": "Bordeaux",
    "distanceBordeaux": 2.8,
    "densiteBornes": 0.9,
    "profilCommune": "grande métropole",
    "marcheImmobilier": "haut de gamme",
    "tauxMaisonLabel": "très dense (collectif)"
  },
  {
    "nom": "Mérignac",
    "slug": "merignac",
    "codeInsee": "33281",
    "codePostal": "33700",
    "population": 78090,
    "latitude": 44.8313,
    "longitude": -0.682,
    "altitude": 25,
    "logements": 38093,
    "logementsMaison": 42,
    "prixM2Moyen": 3290,
    "vehiculesElectriques": 2556,
    "croissanceVE": 21,
    "bornesPubliques": 65,
    "intercommunalite": "Bordeaux Métropole",
    "canton": "Mérignac",
    "distanceBordeaux": 8.1,
    "densiteBornes": 0.8,
    "profilCommune": "grande ville",
    "marcheImmobilier": "intermédiaire",
    "tauxMaisonLabel": "mixte pavillonnaire-collectif"
  },
  {
    "nom": "Pessac",
    "slug": "pessac",
    "codeInsee": "33318",
    "codePostal": "33600",
    "population": 67339,
    "latitude": 44.786,
    "longitude": -0.681,
    "altitude": 12,
    "logements": 32848,
    "logementsMaison": 37,
    "prixM2Moyen": 2900,
    "vehiculesElectriques": 2338,
    "croissanceVE": 30,
    "bornesPubliques": 58,
    "intercommunalite": "Bordeaux Métropole",
    "canton": "Pessac",
    "distanceBordeaux": 9.9,
    "densiteBornes": 0.9,
    "profilCommune": "grande ville",
    "marcheImmobilier": "accessible",
    "tauxMaisonLabel": "majoritairement collectif"
  },
  {
    "nom": "Talence",
    "slug": "talence",
    "codeInsee": "33522",
    "codePostal": "33400",
    "population": 46338,
    "latitude": 44.8061,
    "longitude": -0.5918,
    "altitude": 15,
    "logements": 22604,
    "logementsMaison": 43,
    "prixM2Moyen": 4110,
    "vehiculesElectriques": 2018,
    "croissanceVE": 29,
    "bornesPubliques": 37,
    "intercommunalite": "Bordeaux Métropole",
    "canton": "Talence",
    "distanceBordeaux": 3.7,
    "densiteBornes": 0.8,
    "profilCommune": "grande ville",
    "marcheImmobilier": "intermédiaire",
    "tauxMaisonLabel": "mixte pavillonnaire-collectif"
  },
  {
    "nom": "Villenave-d'Ornon",
    "slug": "villenave-d-ornon",
    "codeInsee": "33550",
    "codePostal": "33140",
    "population": 42545,
    "latitude": 44.7736,
    "longitude": -0.5523,
    "altitude": 10,
    "logements": 20754,
    "logementsMaison": 67,
    "prixM2Moyen": 3600,
    "vehiculesElectriques": 1735,
    "croissanceVE": 31,
    "bornesPubliques": 34,
    "intercommunalite": "Bordeaux Métropole",
    "canton": "Villenave-d'Ornon",
    "distanceBordeaux": 7.4,
    "densiteBornes": 0.8,
    "profilCommune": "grande ville",
    "marcheImmobilier": "intermédiaire",
    "tauxMaisonLabel": "majoritairement pavillonnaire"
  },
  {
    "nom": "Saint-Médard-en-Jalles",
    "slug": "saint-medard-en-jalles",
    "codeInsee": "33449",
    "codePostal": "33160",
    "population": 32910,
    "latitude": 44.8861,
    "longitude": -0.7823,
    "altitude": 27,
    "logements": 14959,
    "logementsMaison": 75,
    "prixM2Moyen": 3540,
    "vehiculesElectriques": 1593,
    "croissanceVE": 30,
    "bornesPubliques": 28,
    "intercommunalite": "Bordeaux Métropole",
    "canton": "Saint-Médard-en-Jalles",
    "distanceBordeaux": 16.9,
    "densiteBornes": 0.9,
    "profilCommune": "ville moyenne",
    "marcheImmobilier": "intermédiaire",
    "tauxMaisonLabel": "majoritairement pavillonnaire"
  },
  {
    "nom": "Bègles",
    "slug": "begles",
    "codeInsee": "33039",
    "codePostal": "33130",
    "population": 31831,
    "latitude": 44.803,
    "longitude": -0.5485,
    "altitude": 8,
    "logements": 14469,
    "logementsMaison": 39,
    "prixM2Moyen": 3140,
    "vehiculesElectriques": 1253,
    "croissanceVE": 29,
    "bornesPubliques": 24,
    "intercommunalite": "Bordeaux Métropole",
    "canton": "Bègles",
    "distanceBordeaux": 4.6,
    "densiteBornes": 0.8,
    "profilCommune": "ville moyenne",
    "marcheImmobilier": "accessible",
    "tauxMaisonLabel": "majoritairement collectif"
  },
  {
    "nom": "La Teste-de-Buch",
    "slug": "la-teste-de-buch",
    "codeInsee": "33529",
    "codePostal": "33115",
    "population": 27566,
    "latitude": 44.586,
    "longitude": -1.1809,
    "altitude": 10,
    "logements": 12530,
    "logementsMaison": 86,
    "prixM2Moyen": 5150,
    "vehiculesElectriques": 1527,
    "croissanceVE": 27,
    "bornesPubliques": 25,
    "intercommunalite": "Communauté d'Agglomération du Bassin d'Arcachon Sud (COBAS)",
    "canton": "La Teste-de-Buch",
    "distanceBordeaux": 55.2,
    "densiteBornes": 0.9,
    "profilCommune": "ville moyenne",
    "marcheImmobilier": "haut de gamme",
    "tauxMaisonLabel": "très pavillonnaire"
  },
  {
    "nom": "Gradignan",
    "slug": "gradignan",
    "codeInsee": "33192",
    "codePostal": "33170",
    "population": 26952,
    "latitude": 44.7681,
    "longitude": -0.6163,
    "altitude": 22,
    "logements": 12251,
    "logementsMaison": 69,
    "prixM2Moyen": 4220,
    "vehiculesElectriques": 1477,
    "croissanceVE": 24,
    "bornesPubliques": 22,
    "intercommunalite": "Bordeaux Métropole",
    "canton": "Gradignan",
    "distanceBordeaux": 8.3,
    "densiteBornes": 0.8,
    "profilCommune": "ville moyenne",
    "marcheImmobilier": "haut de gamme",
    "tauxMaisonLabel": "majoritairement pavillonnaire"
  },
  {
    "nom": "Cenon",
    "slug": "cenon",
    "codeInsee": "33119",
    "codePostal": "33150",
    "population": 26834,
    "latitude": 44.8552,
    "longitude": -0.5223,
    "altitude": 35,
    "logements": 12197,
    "logementsMaison": 67,
    "prixM2Moyen": 3440,
    "vehiculesElectriques": 1255,
    "croissanceVE": 28,
    "bornesPubliques": 26,
    "intercommunalite": "Bordeaux Métropole",
    "canton": "Cenon",
    "distanceBordeaux": 4.9,
    "densiteBornes": 1,
    "profilCommune": "ville moyenne",
    "marcheImmobilier": "intermédiaire",
    "tauxMaisonLabel": "majoritairement pavillonnaire"
  },
  {
    "nom": "Lormont",
    "slug": "lormont",
    "codeInsee": "33249",
    "codePostal": "33310",
    "population": 25769,
    "latitude": 44.8749,
    "longitude": -0.5176,
    "altitude": 40,
    "logements": 11713,
    "logementsMaison": 58,
    "prixM2Moyen": 2900,
    "vehiculesElectriques": 877,
    "croissanceVE": 32,
    "bornesPubliques": 23,
    "intercommunalite": "Bordeaux Métropole",
    "canton": "Lormont",
    "distanceBordeaux": 6.4,
    "densiteBornes": 0.9,
    "profilCommune": "ville moyenne",
    "marcheImmobilier": "accessible",
    "tauxMaisonLabel": "mixte pavillonnaire-collectif"
  },
  {
    "nom": "Le Bouscat",
    "slug": "le-bouscat",
    "codeInsee": "33069",
    "codePostal": "33110",
    "population": 25081,
    "latitude": 44.865,
    "longitude": -0.6033,
    "altitude": 10,
    "logements": 11400,
    "logementsMaison": 66,
    "prixM2Moyen": 4770,
    "vehiculesElectriques": 1372,
    "croissanceVE": 30,
    "bornesPubliques": 21,
    "intercommunalite": "Bordeaux Métropole",
    "canton": "Le Bouscat",
    "distanceBordeaux": 3.6,
    "densiteBornes": 0.8,
    "profilCommune": "ville moyenne",
    "marcheImmobilier": "haut de gamme",
    "tauxMaisonLabel": "majoritairement pavillonnaire"
  },
  {
    "nom": "Libourne",
    "slug": "libourne",
    "codeInsee": "33243",
    "codePostal": "33500",
    "population": 25036,
    "latitude": 44.9125,
    "longitude": -0.2328,
    "altitude": 15,
    "logements": 11380,
    "logementsMaison": 82,
    "prixM2Moyen": 2780,
    "vehiculesElectriques": 950,
    "croissanceVE": 21,
    "bornesPubliques": 24,
    "intercommunalite": "Communauté d'Agglomération du Libournais (La CALI)",
    "canton": "Libourne",
    "distanceBordeaux": 28.5,
    "densiteBornes": 1,
    "profilCommune": "ville moyenne",
    "marcheImmobilier": "accessible",
    "tauxMaisonLabel": "très pavillonnaire"
  },
  {
    "nom": "Eysines",
    "slug": "eysines",
    "codeInsee": "33162",
    "codePostal": "33320",
    "population": 24825,
    "latitude": 44.8779,
    "longitude": -0.646,
    "altitude": 25,
    "logements": 11284,
    "logementsMaison": 62,
    "prixM2Moyen": 3350,
    "vehiculesElectriques": 973,
    "croissanceVE": 21,
    "bornesPubliques": 19,
    "intercommunalite": "Bordeaux Métropole",
    "canton": "Eysines",
    "distanceBordeaux": 6.9,
    "densiteBornes": 0.8,
    "profilCommune": "ville moyenne",
    "marcheImmobilier": "intermédiaire",
    "tauxMaisonLabel": "majoritairement pavillonnaire"
  },
  {
    "nom": "Gujan-Mestras",
    "slug": "gujan-mestras",
    "codeInsee": "33199",
    "codePostal": "33470",
    "population": 22153,
    "latitude": 44.5758,
    "longitude": -1.0813,
    "altitude": 6,
    "logements": 10070,
    "logementsMaison": 89,
    "prixM2Moyen": 5400,
    "vehiculesElectriques": 1278,
    "croissanceVE": 32,
    "bornesPubliques": 22,
    "intercommunalite": "Communauté d'Agglomération du Bassin d'Arcachon Sud (COBAS)",
    "canton": "Gujan-Mestras",
    "distanceBordeaux": 49.2,
    "densiteBornes": 1,
    "profilCommune": "ville moyenne",
    "marcheImmobilier": "haut de gamme",
    "tauxMaisonLabel": "très pavillonnaire"
  },
  {
    "nom": "Bruges",
    "slug": "bruges",
    "codeInsee": "33075",
    "codePostal": "33520",
    "population": 20020,
    "latitude": 44.8893,
    "longitude": -0.6029,
    "altitude": 10,
    "logements": 9100,
    "logementsMaison": 61,
    "prixM2Moyen": 4660,
    "vehiculesElectriques": 823,
    "croissanceVE": 23,
    "bornesPubliques": 18,
    "intercommunalite": "Bordeaux Métropole",
    "canton": "Bruges",
    "distanceBordeaux": 6,
    "densiteBornes": 0.9,
    "profilCommune": "ville moyenne",
    "marcheImmobilier": "haut de gamme",
    "tauxMaisonLabel": "majoritairement pavillonnaire"
  },
  {
    "nom": "Floirac",
    "slug": "floirac",
    "codeInsee": "33167",
    "codePostal": "33270",
    "population": 18300,
    "latitude": 44.8322,
    "longitude": -0.5215,
    "altitude": 20,
    "logements": 8318,
    "logementsMaison": 64,
    "prixM2Moyen": 2890,
    "vehiculesElectriques": 670,
    "croissanceVE": 19,
    "bornesPubliques": 19,
    "intercommunalite": "Bordeaux Métropole",
    "canton": "Floirac",
    "distanceBordeaux": 4.6,
    "densiteBornes": 1,
    "profilCommune": "commune urbaine",
    "marcheImmobilier": "accessible",
    "tauxMaisonLabel": "majoritairement pavillonnaire"
  },
  {
    "nom": "Ambarès-et-Lagrave",
    "slug": "ambares-et-lagrave",
    "codeInsee": "33003",
    "codePostal": "33440",
    "population": 17644,
    "latitude": 44.9517,
    "longitude": -0.5,
    "altitude": 24,
    "logements": 8020,
    "logementsMaison": 64,
    "prixM2Moyen": 3410,
    "vehiculesElectriques": 641,
    "croissanceVE": 33,
    "bornesPubliques": 16,
    "intercommunalite": "Bordeaux Métropole",
    "canton": "Ambarès-et-Lagrave",
    "distanceBordeaux": 14.1,
    "densiteBornes": 0.9,
    "profilCommune": "commune urbaine",
    "marcheImmobilier": "intermédiaire",
    "tauxMaisonLabel": "majoritairement pavillonnaire"
  },
  {
    "nom": "Blanquefort",
    "slug": "blanquefort",
    "codeInsee": "33056",
    "codePostal": "33290",
    "population": 17215,
    "latitude": 44.9216,
    "longitude": -0.61,
    "altitude": 25,
    "logements": 7825,
    "logementsMaison": 65,
    "prixM2Moyen": 3010,
    "vehiculesElectriques": 621,
    "croissanceVE": 18,
    "bornesPubliques": 15,
    "intercommunalite": "Bordeaux Métropole",
    "canton": "Blanquefort",
    "distanceBordeaux": 9.6,
    "densiteBornes": 0.9,
    "profilCommune": "commune urbaine",
    "marcheImmobilier": "accessible",
    "tauxMaisonLabel": "majoritairement pavillonnaire"
  },
  {
    "nom": "Cestas",
    "slug": "cestas",
    "codeInsee": "33122",
    "codePostal": "33610",
    "population": 16666,
    "latitude": 44.7274,
    "longitude": -0.7349,
    "altitude": 26,
    "logements": 7575,
    "logementsMaison": 65,
    "prixM2Moyen": 3280,
    "vehiculesElectriques": 637,
    "croissanceVE": 28,
    "bornesPubliques": 15,
    "intercommunalite": "Communauté de Communes Jalle Eau Bourde",
    "canton": "Cestas",
    "distanceBordeaux": 17.4,
    "densiteBornes": 0.9,
    "profilCommune": "commune urbaine",
    "marcheImmobilier": "intermédiaire",
    "tauxMaisonLabel": "majoritairement pavillonnaire"
  },
  {
    "nom": "Andernos-les-Bains",
    "slug": "andernos-les-bains",
    "codeInsee": "33005",
    "codePostal": "33510",
    "population": 12710,
    "latitude": 44.7529,
    "longitude": -1.082,
    "altitude": 9,
    "logements": 5777,
    "logementsMaison": 87,
    "prixM2Moyen": 5730,
    "vehiculesElectriques": 784,
    "croissanceVE": 20,
    "bornesPubliques": 12,
    "intercommunalite": "Communauté de Communes du Bassin d'Arcachon Nord (COBAN)",
    "canton": "Andernos-les-Bains",
    "distanceBordeaux": 40.8,
    "densiteBornes": 0.9,
    "profilCommune": "commune urbaine",
    "marcheImmobilier": "haut de gamme",
    "tauxMaisonLabel": "très pavillonnaire"
  },
  {
    "nom": "Saint-André-de-Cubzac",
    "slug": "saint-andre-de-cubzac",
    "codeInsee": "33366",
    "codePostal": "33240",
    "population": 12626,
    "latitude": 44.9945,
    "longitude": -0.4378,
    "altitude": 15,
    "logements": 5739,
    "logementsMaison": 55,
    "prixM2Moyen": 3290,
    "vehiculesElectriques": 510,
    "croissanceVE": 22,
    "bornesPubliques": 12,
    "intercommunalite": "Communauté de Communes des Portes de l'Entre-deux-Mers",
    "canton": "Saint-André-de-Cubzac",
    "distanceBordeaux": 20.7,
    "densiteBornes": 1,
    "profilCommune": "commune urbaine",
    "marcheImmobilier": "intermédiaire",
    "tauxMaisonLabel": "mixte pavillonnaire-collectif"
  },
  {
    "nom": "Mios",
    "slug": "mios",
    "codeInsee": "33284",
    "codePostal": "33380",
    "population": 12043,
    "latitude": 44.6105,
    "longitude": -0.8913,
    "altitude": 17,
    "logements": 5474,
    "logementsMaison": 84,
    "prixM2Moyen": 3270,
    "vehiculesElectriques": 498,
    "croissanceVE": 23,
    "bornesPubliques": 14,
    "intercommunalite": "Communauté de Communes du Bassin d'Arcachon Nord (COBAN)",
    "canton": "Mios",
    "distanceBordeaux": 35.3,
    "densiteBornes": 1.2,
    "profilCommune": "commune urbaine",
    "marcheImmobilier": "intermédiaire",
    "tauxMaisonLabel": "très pavillonnaire"
  },
  {
    "nom": "Biganos",
    "slug": "biganos",
    "codeInsee": "33051",
    "codePostal": "33380",
    "population": 11431,
    "latitude": 44.6599,
    "longitude": -0.9582,
    "altitude": 15,
    "logements": 5196,
    "logementsMaison": 89,
    "prixM2Moyen": 3220,
    "vehiculesElectriques": 602,
    "croissanceVE": 22,
    "bornesPubliques": 15,
    "intercommunalite": "Communauté de Communes du Bassin d'Arcachon Nord (COBAN)",
    "canton": "Biganos",
    "distanceBordeaux": 35.9,
    "densiteBornes": 1.3,
    "profilCommune": "commune urbaine",
    "marcheImmobilier": "intermédiaire",
    "tauxMaisonLabel": "très pavillonnaire"
  },
  {
    "nom": "Le Haillan",
    "slug": "le-haillan",
    "codeInsee": "33200",
    "codePostal": "33185",
    "population": 11392,
    "latitude": 44.8713,
    "longitude": -0.6903,
    "altitude": 16,
    "logements": 5178,
    "logementsMaison": 56,
    "prixM2Moyen": 2970,
    "vehiculesElectriques": 448,
    "croissanceVE": 32,
    "bornesPubliques": 13,
    "intercommunalite": "Bordeaux Métropole",
    "canton": "Le Haillan",
    "distanceBordeaux": 9.5,
    "densiteBornes": 1.1,
    "profilCommune": "commune urbaine",
    "marcheImmobilier": "accessible",
    "tauxMaisonLabel": "mixte pavillonnaire-collectif"
  },
  {
    "nom": "Arcachon",
    "slug": "arcachon",
    "codeInsee": "33009",
    "codePostal": "33120",
    "population": 11092,
    "latitude": 44.6515,
    "longitude": -1.1718,
    "altitude": 8,
    "logements": 5042,
    "logementsMaison": 91,
    "prixM2Moyen": 7010,
    "vehiculesElectriques": 857,
    "croissanceVE": 26,
    "bornesPubliques": 13,
    "intercommunalite": "Communauté d'Agglomération du Bassin d'Arcachon Sud (COBAS)",
    "canton": "Arcachon",
    "distanceBordeaux": 51.2,
    "densiteBornes": 1.2,
    "profilCommune": "commune urbaine",
    "marcheImmobilier": "très premium",
    "tauxMaisonLabel": "très pavillonnaire"
  },
  {
    "nom": "Le Taillan-Médoc",
    "slug": "le-taillan-medoc",
    "codeInsee": "33519",
    "codePostal": "33320",
    "population": 11073,
    "latitude": 44.9123,
    "longitude": -0.6785,
    "altitude": 15,
    "logements": 5033,
    "logementsMaison": 55,
    "prixM2Moyen": 3110,
    "vehiculesElectriques": 475,
    "croissanceVE": 31,
    "bornesPubliques": 10,
    "intercommunalite": "Bordeaux Métropole",
    "canton": "Le Taillan-Médoc",
    "distanceBordeaux": 11.4,
    "densiteBornes": 0.9,
    "profilCommune": "commune urbaine",
    "marcheImmobilier": "accessible",
    "tauxMaisonLabel": "mixte pavillonnaire-collectif"
  },
  {
    "nom": "Parempuyre",
    "slug": "parempuyre",
    "codeInsee": "33312",
    "codePostal": "33290",
    "population": 10672,
    "latitude": 44.9548,
    "longitude": -0.5844,
    "altitude": 25,
    "logements": 4851,
    "logementsMaison": 65,
    "prixM2Moyen": 2870,
    "vehiculesElectriques": 480,
    "croissanceVE": 21,
    "bornesPubliques": 9,
    "intercommunalite": "Bordeaux Métropole",
    "canton": "Parempuyre",
    "distanceBordeaux": 13,
    "densiteBornes": 0.8,
    "profilCommune": "commune urbaine",
    "marcheImmobilier": "accessible",
    "tauxMaisonLabel": "majoritairement pavillonnaire"
  },
  {
    "nom": "Léognan",
    "slug": "leognan",
    "codeInsee": "33238",
    "codePostal": "33850",
    "population": 10670,
    "latitude": 44.7236,
    "longitude": -0.6172,
    "altitude": 24,
    "logements": 4850,
    "logementsMaison": 64,
    "prixM2Moyen": 2960,
    "vehiculesElectriques": 482,
    "croissanceVE": 29,
    "bornesPubliques": 13,
    "intercommunalite": "Communauté de Communes des Portes de l'Entre-deux-Mers",
    "canton": "Léognan",
    "distanceBordeaux": 13,
    "densiteBornes": 1.2,
    "profilCommune": "commune urbaine",
    "marcheImmobilier": "accessible",
    "tauxMaisonLabel": "majoritairement pavillonnaire"
  },
  {
    "nom": "Saint-Loubès",
    "slug": "saint-loubes",
    "codeInsee": "33433",
    "codePostal": "33450",
    "population": 10027,
    "latitude": 44.9223,
    "longitude": -0.4257,
    "altitude": 24,
    "logements": 4558,
    "logementsMaison": 64,
    "prixM2Moyen": 3640,
    "vehiculesElectriques": 430,
    "croissanceVE": 19,
    "bornesPubliques": 13,
    "intercommunalite": "Communauté de Communes des Portes de l'Entre-deux-Mers",
    "canton": "Saint-Loubès",
    "distanceBordeaux": 15.3,
    "densiteBornes": 1.3,
    "profilCommune": "commune urbaine",
    "marcheImmobilier": "intermédiaire",
    "tauxMaisonLabel": "majoritairement pavillonnaire"
  },
  {
    "nom": "Saint-Jean-d'Illac",
    "slug": "saint-jean-d-illac",
    "codeInsee": "33422",
    "codePostal": "33127",
    "population": 9616,
    "latitude": 44.7973,
    "longitude": -0.8156,
    "altitude": 19,
    "logements": 4371,
    "logementsMaison": 89,
    "prixM2Moyen": 3400,
    "vehiculesElectriques": 509,
    "croissanceVE": 20,
    "bornesPubliques": 12,
    "intercommunalite": "Communauté de Communes Jalle Eau Bourde",
    "canton": "Saint-Jean-d'Illac",
    "distanceBordeaux": 19.2,
    "densiteBornes": 1.2,
    "profilCommune": "commune résidentielle",
    "marcheImmobilier": "intermédiaire",
    "tauxMaisonLabel": "très pavillonnaire"
  },
  {
    "nom": "Audenge",
    "slug": "audenge",
    "codeInsee": "33019",
    "codePostal": "33980",
    "population": 9596,
    "latitude": 44.7133,
    "longitude": -0.9533,
    "altitude": 5,
    "logements": 4362,
    "logementsMaison": 91,
    "prixM2Moyen": 2940,
    "vehiculesElectriques": 448,
    "croissanceVE": 32,
    "bornesPubliques": 10,
    "intercommunalite": "Communauté de Communes du Bassin d'Arcachon Nord (COBAN)",
    "canton": "Audenge",
    "distanceBordeaux": 32.6,
    "densiteBornes": 1,
    "profilCommune": "commune résidentielle",
    "marcheImmobilier": "accessible",
    "tauxMaisonLabel": "très pavillonnaire"
  },
  {
    "nom": "Le Teich",
    "slug": "le-teich",
    "codeInsee": "33527",
    "codePostal": "33470",
    "population": 9180,
    "latitude": 44.5805,
    "longitude": -1.0234,
    "altitude": 19,
    "logements": 4173,
    "logementsMaison": 91,
    "prixM2Moyen": 3240,
    "vehiculesElectriques": 481,
    "croissanceVE": 32,
    "bornesPubliques": 9,
    "intercommunalite": "Communauté d'Agglomération du Bassin d'Arcachon Sud (COBAS)",
    "canton": "Le Teich",
    "distanceBordeaux": 45.3,
    "densiteBornes": 1,
    "profilCommune": "commune résidentielle",
    "marcheImmobilier": "intermédiaire",
    "tauxMaisonLabel": "très pavillonnaire"
  },
  {
    "nom": "Artigues-près-Bordeaux",
    "slug": "artigues-pres-bordeaux",
    "codeInsee": "33013",
    "codePostal": "33370",
    "population": 8687,
    "latitude": 44.8592,
    "longitude": -0.4878,
    "altitude": 23,
    "logements": 3949,
    "logementsMaison": 63,
    "prixM2Moyen": 3490,
    "vehiculesElectriques": 388,
    "croissanceVE": 23,
    "bornesPubliques": 12,
    "intercommunalite": "Bordeaux Métropole",
    "canton": "Artigues-près-Bordeaux",
    "distanceBordeaux": 7.6,
    "densiteBornes": 1.4,
    "profilCommune": "commune résidentielle",
    "marcheImmobilier": "intermédiaire",
    "tauxMaisonLabel": "majoritairement pavillonnaire"
  },
  {
    "nom": "Coutras",
    "slug": "coutras",
    "codeInsee": "33138",
    "codePostal": "33230",
    "population": 8678,
    "latitude": 45.0408,
    "longitude": -0.1003,
    "altitude": 70,
    "logements": 3945,
    "logementsMaison": 91,
    "prixM2Moyen": 2550,
    "vehiculesElectriques": 407,
    "croissanceVE": 22,
    "bornesPubliques": 13,
    "intercommunalite": "Communauté d'Agglomération du Libournais (La CALI)",
    "canton": "Coutras",
    "distanceBordeaux": 43.9,
    "densiteBornes": 1.5,
    "profilCommune": "commune résidentielle",
    "marcheImmobilier": "accessible",
    "tauxMaisonLabel": "très pavillonnaire"
  },
  {
    "nom": "Bassens",
    "slug": "bassens",
    "codeInsee": "33032",
    "codePostal": "33530",
    "population": 8435,
    "latitude": 44.9068,
    "longitude": -0.526,
    "altitude": 23,
    "logements": 3834,
    "logementsMaison": 63,
    "prixM2Moyen": 3020,
    "vehiculesElectriques": 316,
    "croissanceVE": 28,
    "bornesPubliques": 13,
    "intercommunalite": "Bordeaux Métropole",
    "canton": "Bassens",
    "distanceBordeaux": 8.7,
    "densiteBornes": 1.5,
    "profilCommune": "commune résidentielle",
    "marcheImmobilier": "accessible",
    "tauxMaisonLabel": "majoritairement pavillonnaire"
  },
  {
    "nom": "Carbon-Blanc",
    "slug": "carbon-blanc",
    "codeInsee": "33096",
    "codePostal": "33560",
    "population": 8331,
    "latitude": 44.9019,
    "longitude": -0.5008,
    "altitude": 18,
    "logements": 3787,
    "logementsMaison": 58,
    "prixM2Moyen": 3540,
    "vehiculesElectriques": 340,
    "croissanceVE": 33,
    "bornesPubliques": 12,
    "intercommunalite": "Bordeaux Métropole",
    "canton": "Carbon-Blanc",
    "distanceBordeaux": 9.4,
    "densiteBornes": 1.4,
    "profilCommune": "commune résidentielle",
    "marcheImmobilier": "intermédiaire",
    "tauxMaisonLabel": "mixte pavillonnaire-collectif"
  },
  {
    "nom": "Salles",
    "slug": "salles",
    "codeInsee": "33498",
    "codePostal": "33770",
    "population": 8208,
    "latitude": 44.536,
    "longitude": -0.8899,
    "altitude": 15,
    "logements": 3731,
    "logementsMaison": 84,
    "prixM2Moyen": 2900,
    "vehiculesElectriques": 328,
    "croissanceVE": 19,
    "bornesPubliques": 8,
    "intercommunalite": "Communauté de Communes des Portes de l'Entre-deux-Mers",
    "canton": "Salles",
    "distanceBordeaux": 41.6,
    "densiteBornes": 1,
    "profilCommune": "commune résidentielle",
    "marcheImmobilier": "accessible",
    "tauxMaisonLabel": "très pavillonnaire"
  },
  {
    "nom": "Martignas-sur-Jalle",
    "slug": "martignas-sur-jalle",
    "codeInsee": "33273",
    "codePostal": "33127",
    "population": 8056,
    "latitude": 44.8451,
    "longitude": -0.8006,
    "altitude": 8,
    "logements": 3662,
    "logementsMaison": 84,
    "prixM2Moyen": 3360,
    "vehiculesElectriques": 352,
    "croissanceVE": 29,
    "bornesPubliques": 10,
    "intercommunalite": "Bordeaux Métropole",
    "canton": "Martignas-sur-Jalle",
    "distanceBordeaux": 17.5,
    "densiteBornes": 1.2,
    "profilCommune": "commune résidentielle",
    "marcheImmobilier": "intermédiaire",
    "tauxMaisonLabel": "très pavillonnaire"
  },
  {
    "nom": "Lège-Cap-Ferret",
    "slug": "lege-cap-ferret",
    "codeInsee": "33236",
    "codePostal": "33950",
    "population": 7909,
    "latitude": 44.7452,
    "longitude": -1.174,
    "altitude": 11,
    "logements": 3595,
    "logementsMaison": 87,
    "prixM2Moyen": 10150,
    "vehiculesElectriques": 673,
    "croissanceVE": 24,
    "bornesPubliques": 9,
    "intercommunalite": "Communauté de Communes du Bassin d'Arcachon Nord (COBAN)",
    "canton": "Lège-Cap-Ferret",
    "distanceBordeaux": 48.1,
    "densiteBornes": 1.1,
    "profilCommune": "commune résidentielle",
    "marcheImmobilier": "très premium",
    "tauxMaisonLabel": "très pavillonnaire"
  },
  {
    "nom": "Saint-Aubin-de-Médoc",
    "slug": "saint-aubin-de-medoc",
    "codeInsee": "33376",
    "codePostal": "33160",
    "population": 7769,
    "latitude": 44.9343,
    "longitude": -0.7478,
    "altitude": 21,
    "logements": 3531,
    "logementsMaison": 61,
    "prixM2Moyen": 3560,
    "vehiculesElectriques": 380,
    "croissanceVE": 33,
    "bornesPubliques": 9,
    "intercommunalite": "Bordeaux Métropole",
    "canton": "Saint-Aubin-de-Médoc",
    "distanceBordeaux": 17.1,
    "densiteBornes": 1.2,
    "profilCommune": "commune résidentielle",
    "marcheImmobilier": "intermédiaire",
    "tauxMaisonLabel": "majoritairement pavillonnaire"
  },
  {
    "nom": "Langon",
    "slug": "langon",
    "codeInsee": "33227",
    "codePostal": "33210",
    "population": 7674,
    "latitude": 44.5355,
    "longitude": -0.2422,
    "altitude": 60,
    "logements": 3488,
    "logementsMaison": 85,
    "prixM2Moyen": 3480,
    "vehiculesElectriques": 353,
    "croissanceVE": 20,
    "bornesPubliques": 12,
    "intercommunalite": "Communauté de Communes du Sud Gironde",
    "canton": "Langon",
    "distanceBordeaux": 42.9,
    "densiteBornes": 1.6,
    "profilCommune": "commune résidentielle",
    "marcheImmobilier": "intermédiaire",
    "tauxMaisonLabel": "très pavillonnaire"
  },
  {
    "nom": "Lanton",
    "slug": "lanton",
    "codeInsee": "33229",
    "codePostal": "33138",
    "population": 7337,
    "latitude": 44.7719,
    "longitude": -0.9799,
    "altitude": 7,
    "logements": 3335,
    "logementsMaison": 86,
    "prixM2Moyen": 2880,
    "vehiculesElectriques": 369,
    "croissanceVE": 33,
    "bornesPubliques": 11,
    "intercommunalite": "Communauté de Communes du Bassin d'Arcachon Nord (COBAN)",
    "canton": "Lanton",
    "distanceBordeaux": 32.5,
    "densiteBornes": 1.5,
    "profilCommune": "commune résidentielle",
    "marcheImmobilier": "accessible",
    "tauxMaisonLabel": "très pavillonnaire"
  },
  {
    "nom": "Le Pian-Médoc",
    "slug": "le-pian-medoc",
    "codeInsee": "33322",
    "codePostal": "33290",
    "population": 7292,
    "latitude": 44.9555,
    "longitude": -0.6737,
    "altitude": 24,
    "logements": 3315,
    "logementsMaison": 64,
    "prixM2Moyen": 2930,
    "vehiculesElectriques": 278,
    "croissanceVE": 26,
    "bornesPubliques": 8,
    "intercommunalite": "Bordeaux Métropole",
    "canton": "Le Pian-Médoc",
    "distanceBordeaux": 15.1,
    "densiteBornes": 1.1,
    "profilCommune": "commune résidentielle",
    "marcheImmobilier": "accessible",
    "tauxMaisonLabel": "majoritairement pavillonnaire"
  },
  {
    "nom": "Cadaujac",
    "slug": "cadaujac",
    "codeInsee": "33080",
    "codePostal": "33140",
    "population": 6909,
    "latitude": 44.7468,
    "longitude": -0.5316,
    "altitude": 28,
    "logements": 3140,
    "logementsMaison": 68,
    "prixM2Moyen": 3140,
    "vehiculesElectriques": 267,
    "croissanceVE": 27,
    "bornesPubliques": 11,
    "intercommunalite": "Bordeaux Métropole",
    "canton": "Cadaujac",
    "distanceBordeaux": 10.8,
    "densiteBornes": 1.6,
    "profilCommune": "commune résidentielle",
    "marcheImmobilier": "accessible",
    "tauxMaisonLabel": "majoritairement pavillonnaire"
  },
  {
    "nom": "Arès",
    "slug": "ares",
    "codeInsee": "33011",
    "codePostal": "33740",
    "population": 6482,
    "latitude": 44.7997,
    "longitude": -1.0837,
    "altitude": 19,
    "logements": 2946,
    "logementsMaison": 83,
    "prixM2Moyen": 3460,
    "vehiculesElectriques": 324,
    "croissanceVE": 22,
    "bornesPubliques": 10,
    "intercommunalite": "Communauté de Communes du Bassin d'Arcachon Nord (COBAN)",
    "canton": "Arès",
    "distanceBordeaux": 40,
    "densiteBornes": 1.5,
    "profilCommune": "commune résidentielle",
    "marcheImmobilier": "intermédiaire",
    "tauxMaisonLabel": "très pavillonnaire"
  },
  {
    "nom": "Izon",
    "slug": "izon",
    "codeInsee": "33207",
    "codePostal": "33450",
    "population": 6374,
    "latitude": 44.9188,
    "longitude": -0.3561,
    "altitude": 20,
    "logements": 2897,
    "logementsMaison": 60,
    "prixM2Moyen": 3280,
    "vehiculesElectriques": 251,
    "croissanceVE": 23,
    "bornesPubliques": 6,
    "intercommunalite": "Communauté d'Agglomération du Libournais (La CALI)",
    "canton": "Izon",
    "distanceBordeaux": 19.8,
    "densiteBornes": 0.9,
    "profilCommune": "commune résidentielle",
    "marcheImmobilier": "intermédiaire",
    "tauxMaisonLabel": "majoritairement pavillonnaire"
  },
  {
    "nom": "Belin-Béliet",
    "slug": "belin-beliet",
    "codeInsee": "33042",
    "codePostal": "33830",
    "population": 6275,
    "latitude": 44.4959,
    "longitude": -0.7989,
    "altitude": 37,
    "logements": 2852,
    "logementsMaison": 86,
    "prixM2Moyen": 3170,
    "vehiculesElectriques": 327,
    "croissanceVE": 21,
    "bornesPubliques": 8,
    "intercommunalite": "Communauté de Communes des Portes de l'Entre-deux-Mers",
    "canton": "Belin-Béliet",
    "distanceBordeaux": 41.8,
    "densiteBornes": 1.3,
    "profilCommune": "commune résidentielle",
    "marcheImmobilier": "accessible",
    "tauxMaisonLabel": "très pavillonnaire"
  },
  {
    "nom": "Saint-Denis-de-Pile",
    "slug": "saint-denis-de-pile",
    "codeInsee": "33393",
    "codePostal": "33910",
    "population": 5955,
    "latitude": 44.9893,
    "longitude": -0.1833,
    "altitude": 68,
    "logements": 2707,
    "logementsMaison": 92,
    "prixM2Moyen": 2660,
    "vehiculesElectriques": 239,
    "croissanceVE": 25,
    "bornesPubliques": 10,
    "intercommunalite": "Communauté d'Agglomération du Libournais (La CALI)",
    "canton": "Saint-Denis-de-Pile",
    "distanceBordeaux": 35.4,
    "densiteBornes": 1.7,
    "profilCommune": "commune résidentielle",
    "marcheImmobilier": "accessible",
    "tauxMaisonLabel": "très pavillonnaire"
  },
  {
    "nom": "Lesparre-Médoc",
    "slug": "lesparre-medoc",
    "codeInsee": "33240",
    "codePostal": "33340",
    "population": 5872,
    "latitude": 45.2796,
    "longitude": -0.9235,
    "altitude": 19,
    "logements": 2669,
    "logementsMaison": 93,
    "prixM2Moyen": 2910,
    "vehiculesElectriques": 244,
    "croissanceVE": 32,
    "bornesPubliques": 9,
    "intercommunalite": "Communauté de Communes Médoc Estuaire",
    "canton": "Lesparre-Médoc",
    "distanceBordeaux": 56.1,
    "densiteBornes": 1.5,
    "profilCommune": "commune résidentielle",
    "marcheImmobilier": "accessible",
    "tauxMaisonLabel": "très pavillonnaire"
  },
  {
    "nom": "Le Barp",
    "slug": "le-barp",
    "codeInsee": "33029",
    "codePostal": "33114",
    "population": 5806,
    "latitude": 44.6297,
    "longitude": -0.7437,
    "altitude": 19,
    "logements": 2639,
    "logementsMaison": 59,
    "prixM2Moyen": 2950,
    "vehiculesElectriques": 242,
    "croissanceVE": 22,
    "bornesPubliques": 11,
    "intercommunalite": "Communauté de Communes des Portes de l'Entre-deux-Mers",
    "canton": "Le Barp",
    "distanceBordeaux": 26.5,
    "densiteBornes": 1.9,
    "profilCommune": "commune résidentielle",
    "marcheImmobilier": "accessible",
    "tauxMaisonLabel": "mixte pavillonnaire-collectif"
  },
  {
    "nom": "Canéjan",
    "slug": "canejan",
    "codeInsee": "33090",
    "codePostal": "33610",
    "population": 5756,
    "latitude": 44.7572,
    "longitude": -0.659,
    "altitude": 21,
    "logements": 2616,
    "logementsMaison": 61,
    "prixM2Moyen": 3020,
    "vehiculesElectriques": 211,
    "croissanceVE": 31,
    "bornesPubliques": 6,
    "intercommunalite": "Communauté de Communes Jalle Eau Bourde",
    "canton": "Canéjan",
    "distanceBordeaux": 11,
    "densiteBornes": 1,
    "profilCommune": "commune résidentielle",
    "marcheImmobilier": "accessible",
    "tauxMaisonLabel": "majoritairement pavillonnaire"
  },
  {
    "nom": "Lacanau",
    "slug": "lacanau",
    "codeInsee": "33214",
    "codePostal": "33680",
    "population": 5739,
    "latitude": 44.9879,
    "longitude": -1.096,
    "altitude": 14,
    "logements": 2609,
    "logementsMaison": 91,
    "prixM2Moyen": 3260,
    "vehiculesElectriques": 265,
    "croissanceVE": 24,
    "bornesPubliques": 7,
    "intercommunalite": "Communauté de Communes des Portes de l'Entre-deux-Mers",
    "canton": "Lacanau",
    "distanceBordeaux": 44,
    "densiteBornes": 1.2,
    "profilCommune": "commune résidentielle",
    "marcheImmobilier": "intermédiaire",
    "tauxMaisonLabel": "très pavillonnaire"
  },
  {
    "nom": "Marcheprime",
    "slug": "marcheprime",
    "codeInsee": "33555",
    "codePostal": "33380",
    "population": 5696,
    "latitude": 44.7033,
    "longitude": -0.8557,
    "altitude": 10,
    "logements": 2589,
    "logementsMaison": 83,
    "prixM2Moyen": 2890,
    "vehiculesElectriques": 275,
    "croissanceVE": 26,
    "bornesPubliques": 9,
    "intercommunalite": "Communauté de Communes du Bassin d'Arcachon Nord (COBAN)",
    "canton": "Marcheprime",
    "distanceBordeaux": 26.5,
    "densiteBornes": 1.6,
    "profilCommune": "commune résidentielle",
    "marcheImmobilier": "accessible",
    "tauxMaisonLabel": "très pavillonnaire"
  },
  {
    "nom": "Ludon-Médoc",
    "slug": "ludon-medoc",
    "codeInsee": "33256",
    "codePostal": "33290",
    "population": 5578,
    "latitude": 44.9814,
    "longitude": -0.5903,
    "altitude": 21,
    "logements": 2535,
    "logementsMaison": 61,
    "prixM2Moyen": 2950,
    "vehiculesElectriques": 210,
    "croissanceVE": 26,
    "bornesPubliques": 11,
    "intercommunalite": "Bordeaux Métropole",
    "canton": "Ludon-Médoc",
    "distanceBordeaux": 16,
    "densiteBornes": 2,
    "profilCommune": "commune résidentielle",
    "marcheImmobilier": "accessible",
    "tauxMaisonLabel": "majoritairement pavillonnaire"
  },
  {
    "nom": "Tresses",
    "slug": "tresses",
    "codeInsee": "33535",
    "codePostal": "33370",
    "population": 5290,
    "latitude": 44.8455,
    "longitude": -0.4741,
    "altitude": 16,
    "logements": 2405,
    "logementsMaison": 56,
    "prixM2Moyen": 3340,
    "vehiculesElectriques": 250,
    "croissanceVE": 18,
    "bornesPubliques": 9,
    "intercommunalite": "Bordeaux Métropole",
    "canton": "Tresses",
    "distanceBordeaux": 8.3,
    "densiteBornes": 1.7,
    "profilCommune": "commune résidentielle",
    "marcheImmobilier": "intermédiaire",
    "tauxMaisonLabel": "mixte pavillonnaire-collectif"
  },
  {
    "nom": "Pauillac",
    "slug": "pauillac",
    "codeInsee": "33314",
    "codePostal": "33250",
    "population": 5190,
    "latitude": 45.1983,
    "longitude": -0.755,
    "altitude": 20,
    "logements": 2359,
    "logementsMaison": 60,
    "prixM2Moyen": 3390,
    "vehiculesElectriques": 223,
    "croissanceVE": 30,
    "bornesPubliques": 7,
    "intercommunalite": "Communauté de Communes Médoc Estuaire",
    "canton": "Pauillac",
    "distanceBordeaux": 42.4,
    "densiteBornes": 1.3,
    "profilCommune": "commune résidentielle",
    "marcheImmobilier": "intermédiaire",
    "tauxMaisonLabel": "majoritairement pavillonnaire"
  },
  {
    "nom": "Blaye",
    "slug": "blaye",
    "codeInsee": "33058",
    "codePostal": "33390",
    "population": 5066,
    "latitude": 45.1311,
    "longitude": -0.667,
    "altitude": 21,
    "logements": 2303,
    "logementsMaison": 61,
    "prixM2Moyen": 3020,
    "vehiculesElectriques": 234,
    "croissanceVE": 20,
    "bornesPubliques": 11,
    "intercommunalite": "Communauté de Communes des Portes de l'Entre-deux-Mers",
    "canton": "Blaye",
    "distanceBordeaux": 33.3,
    "densiteBornes": 2.2,
    "profilCommune": "commune résidentielle",
    "marcheImmobilier": "accessible",
    "tauxMaisonLabel": "majoritairement pavillonnaire"
  },
  {
    "nom": "Créon",
    "slug": "creon",
    "codeInsee": "33140",
    "codePostal": "33670",
    "population": 4950,
    "latitude": 44.7688,
    "longitude": -0.3444,
    "altitude": 16,
    "logements": 2250,
    "logementsMaison": 56,
    "prixM2Moyen": 2980,
    "vehiculesElectriques": 200,
    "croissanceVE": 18,
    "bornesPubliques": 8,
    "intercommunalite": "Communauté de Communes des Portes de l'Entre-deux-Mers",
    "canton": "Créon",
    "distanceBordeaux": 20,
    "densiteBornes": 1.6,
    "profilCommune": "bourg périurbain",
    "marcheImmobilier": "accessible",
    "tauxMaisonLabel": "mixte pavillonnaire-collectif"
  },
  {
    "nom": "Sainte-Eulalie",
    "slug": "sainte-eulalie",
    "codeInsee": "33397",
    "codePostal": "33560",
    "population": 4915,
    "latitude": 44.9027,
    "longitude": -0.48,
    "altitude": 23,
    "logements": 2234,
    "logementsMaison": 63,
    "prixM2Moyen": 2980,
    "vehiculesElectriques": 194,
    "croissanceVE": 19,
    "bornesPubliques": 5,
    "intercommunalite": "Bordeaux Métropole",
    "canton": "Sainte-Eulalie",
    "distanceBordeaux": 10.6,
    "densiteBornes": 1,
    "profilCommune": "bourg périurbain",
    "marcheImmobilier": "accessible",
    "tauxMaisonLabel": "majoritairement pavillonnaire"
  },
  {
    "nom": "Saint-Laurent-Médoc",
    "slug": "saint-laurent-medoc",
    "codeInsee": "33424",
    "codePostal": "33112",
    "population": 4914,
    "latitude": 45.1402,
    "longitude": -0.8557,
    "altitude": 8,
    "logements": 2234,
    "logementsMaison": 84,
    "prixM2Moyen": 2990,
    "vehiculesElectriques": 204,
    "croissanceVE": 29,
    "bornesPubliques": 7,
    "intercommunalite": "Communauté de Communes des Portes de l'Entre-deux-Mers",
    "canton": "Saint-Laurent-Médoc",
    "distanceBordeaux": 40,
    "densiteBornes": 1.4,
    "profilCommune": "bourg périurbain",
    "marcheImmobilier": "accessible",
    "tauxMaisonLabel": "très pavillonnaire"
  },
  {
    "nom": "Castelnau-de-Médoc",
    "slug": "castelnau-de-medoc",
    "codeInsee": "33104",
    "codePostal": "33480",
    "population": 4907,
    "latitude": 45.0033,
    "longitude": -0.8162,
    "altitude": 12,
    "logements": 2230,
    "logementsMaison": 87,
    "prixM2Moyen": 3240,
    "vehiculesElectriques": 266,
    "croissanceVE": 28,
    "bornesPubliques": 6,
    "intercommunalite": "Communauté de Communes des Portes de l'Entre-deux-Mers",
    "canton": "Castelnau-de-Médoc",
    "distanceBordeaux": 26.2,
    "densiteBornes": 1.2,
    "profilCommune": "bourg périurbain",
    "marcheImmobilier": "intermédiaire",
    "tauxMaisonLabel": "très pavillonnaire"
  },
  {
    "nom": "Saint-Sulpice-et-Cameyrac",
    "slug": "saint-sulpice-et-cameyrac",
    "codeInsee": "33483",
    "codePostal": "33450",
    "population": 4881,
    "latitude": 44.9053,
    "longitude": -0.3803,
    "altitude": 15,
    "logements": 2219,
    "logementsMaison": 55,
    "prixM2Moyen": 3070,
    "vehiculesElectriques": 189,
    "croissanceVE": 24,
    "bornesPubliques": 8,
    "intercommunalite": "Communauté d'Agglomération du Libournais (La CALI)",
    "canton": "Saint-Sulpice-et-Cameyrac",
    "distanceBordeaux": 17.4,
    "densiteBornes": 1.6,
    "profilCommune": "bourg périurbain",
    "marcheImmobilier": "accessible",
    "tauxMaisonLabel": "mixte pavillonnaire-collectif"
  },
  {
    "nom": "Bazas",
    "slug": "bazas",
    "codeInsee": "33036",
    "codePostal": "33430",
    "population": 4854,
    "latitude": 44.4409,
    "longitude": -0.2177,
    "altitude": 70,
    "logements": 2206,
    "logementsMaison": 85,
    "prixM2Moyen": 2910,
    "vehiculesElectriques": 237,
    "croissanceVE": 26,
    "bornesPubliques": 8,
    "intercommunalite": "Communauté de Communes des Portes de l'Entre-deux-Mers",
    "canton": "Bazas",
    "distanceBordeaux": 52.6,
    "densiteBornes": 1.6,
    "profilCommune": "bourg périurbain",
    "marcheImmobilier": "accessible",
    "tauxMaisonLabel": "très pavillonnaire"
  },
  {
    "nom": "Sadirac",
    "slug": "sadirac",
    "codeInsee": "33363",
    "codePostal": "33670",
    "population": 4769,
    "latitude": 44.787,
    "longitude": -0.3925,
    "altitude": 25,
    "logements": 2168,
    "logementsMaison": 65,
    "prixM2Moyen": 3340,
    "vehiculesElectriques": 218,
    "croissanceVE": 30,
    "bornesPubliques": 10,
    "intercommunalite": "Communauté de Communes des Portes de l'Entre-deux-Mers",
    "canton": "Sadirac",
    "distanceBordeaux": 15.8,
    "densiteBornes": 2.1,
    "profilCommune": "bourg périurbain",
    "marcheImmobilier": "intermédiaire",
    "tauxMaisonLabel": "majoritairement pavillonnaire"
  },
  {
    "nom": "Vayres",
    "slug": "vayres",
    "codeInsee": "33539",
    "codePostal": "33870",
    "population": 4615,
    "latitude": 44.8908,
    "longitude": -0.326,
    "altitude": 18,
    "logements": 2098,
    "logementsMaison": 58,
    "prixM2Moyen": 3100,
    "vehiculesElectriques": 180,
    "croissanceVE": 25,
    "bornesPubliques": 7,
    "intercommunalite": "Communauté d'Agglomération du Libournais (La CALI)",
    "canton": "Vayres",
    "distanceBordeaux": 20.8,
    "densiteBornes": 1.5,
    "profilCommune": "bourg périurbain",
    "marcheImmobilier": "accessible",
    "tauxMaisonLabel": "mixte pavillonnaire-collectif"
  },
  {
    "nom": "Macau",
    "slug": "macau",
    "codeInsee": "33262",
    "codePostal": "33460",
    "population": 4576,
    "latitude": 45.0112,
    "longitude": -0.6086,
    "altitude": 15,
    "logements": 2080,
    "logementsMaison": 55,
    "prixM2Moyen": 3290,
    "vehiculesElectriques": 160,
    "croissanceVE": 20,
    "bornesPubliques": 10,
    "intercommunalite": "Communauté de Communes Médoc Estuaire",
    "canton": "Macau",
    "distanceBordeaux": 19.4,
    "densiteBornes": 2.2,
    "profilCommune": "bourg périurbain",
    "marcheImmobilier": "intermédiaire",
    "tauxMaisonLabel": "mixte pavillonnaire-collectif"
  },
  {
    "nom": "Pineuilh",
    "slug": "pineuilh",
    "codeInsee": "33324",
    "codePostal": "33220",
    "population": 4490,
    "latitude": 44.8242,
    "longitude": 0.2284,
    "altitude": 63,
    "logements": 2041,
    "logementsMaison": 92,
    "prixM2Moyen": 3150,
    "vehiculesElectriques": 240,
    "croissanceVE": 29,
    "bornesPubliques": 5,
    "intercommunalite": "Communauté de Communes des Portes de l'Entre-deux-Mers",
    "canton": "Pineuilh",
    "distanceBordeaux": 63.7,
    "densiteBornes": 1.1,
    "profilCommune": "bourg périurbain",
    "marcheImmobilier": "accessible",
    "tauxMaisonLabel": "très pavillonnaire"
  },
  {
    "nom": "La Réole",
    "slug": "la-reole",
    "codeInsee": "33352",
    "codePostal": "33190",
    "population": 4487,
    "latitude": 44.5869,
    "longitude": -0.0447,
    "altitude": 67,
    "logements": 2040,
    "logementsMaison": 87,
    "prixM2Moyen": 3040,
    "vehiculesElectriques": 209,
    "croissanceVE": 20,
    "bornesPubliques": 10,
    "intercommunalite": "Communauté de Communes du Sud Gironde",
    "canton": "La Réole",
    "distanceBordeaux": 50.6,
    "densiteBornes": 2.2,
    "profilCommune": "bourg périurbain",
    "marcheImmobilier": "accessible",
    "tauxMaisonLabel": "très pavillonnaire"
  },
  {
    "nom": "Carignan-de-Bordeaux",
    "slug": "carignan-de-bordeaux",
    "codeInsee": "33099",
    "codePostal": "33360",
    "population": 4388,
    "latitude": 44.8093,
    "longitude": -0.4739,
    "altitude": 20,
    "logements": 1995,
    "logementsMaison": 60,
    "prixM2Moyen": 3010,
    "vehiculesElectriques": 191,
    "croissanceVE": 23,
    "bornesPubliques": 5,
    "intercommunalite": "Communauté de Communes des Portes de l'Entre-deux-Mers",
    "canton": "Carignan-de-Bordeaux",
    "distanceBordeaux": 8.9,
    "densiteBornes": 1.1,
    "profilCommune": "bourg périurbain",
    "marcheImmobilier": "accessible",
    "tauxMaisonLabel": "majoritairement pavillonnaire"
  },
  {
    "nom": "La Brède",
    "slug": "la-brede",
    "codeInsee": "33213",
    "codePostal": "33650",
    "population": 4386,
    "latitude": 44.6777,
    "longitude": -0.5396,
    "altitude": 28,
    "logements": 1994,
    "logementsMaison": 68,
    "prixM2Moyen": 2950,
    "vehiculesElectriques": 202,
    "croissanceVE": 21,
    "bornesPubliques": 7,
    "intercommunalite": "Communauté de Communes des Portes de l'Entre-deux-Mers",
    "canton": "La Brède",
    "distanceBordeaux": 18.1,
    "densiteBornes": 1.6,
    "profilCommune": "bourg périurbain",
    "marcheImmobilier": "accessible",
    "tauxMaisonLabel": "majoritairement pavillonnaire"
  },
  {
    "nom": "Arsac",
    "slug": "arsac",
    "codeInsee": "33012",
    "codePostal": "33460",
    "population": 4124,
    "latitude": 44.9869,
    "longitude": -0.7018,
    "altitude": 18,
    "logements": 1875,
    "logementsMaison": 58,
    "prixM2Moyen": 3250,
    "vehiculesElectriques": 141,
    "croissanceVE": 19,
    "bornesPubliques": 7,
    "intercommunalite": "Communauté de Communes Médoc Estuaire",
    "canton": "Arsac",
    "distanceBordeaux": 19.2,
    "densiteBornes": 1.7,
    "profilCommune": "bourg périurbain",
    "marcheImmobilier": "intermédiaire",
    "tauxMaisonLabel": "mixte pavillonnaire-collectif"
  },
  {
    "nom": "Hourtin",
    "slug": "hourtin",
    "codeInsee": "33203",
    "codePostal": "33990",
    "population": 4045,
    "latitude": 45.1831,
    "longitude": -1.0534,
    "altitude": 7,
    "logements": 1839,
    "logementsMaison": 87,
    "prixM2Moyen": 3320,
    "vehiculesElectriques": 221,
    "croissanceVE": 18,
    "bornesPubliques": 6,
    "intercommunalite": "Communauté de Communes des Portes de l'Entre-deux-Mers",
    "canton": "Hourtin",
    "distanceBordeaux": 53.5,
    "densiteBornes": 1.5,
    "profilCommune": "bourg périurbain",
    "marcheImmobilier": "intermédiaire",
    "tauxMaisonLabel": "très pavillonnaire"
  },
  {
    "nom": "Bouliac",
    "slug": "bouliac",
    "codeInsee": "33065",
    "codePostal": "33270",
    "population": 3804,
    "latitude": 44.8165,
    "longitude": -0.5026,
    "altitude": 21,
    "logements": 1729,
    "logementsMaison": 61,
    "prixM2Moyen": 3560,
    "vehiculesElectriques": 174,
    "croissanceVE": 32,
    "bornesPubliques": 6,
    "intercommunalite": "Bordeaux Métropole",
    "canton": "Bouliac",
    "distanceBordeaux": 6.5,
    "densiteBornes": 1.6,
    "profilCommune": "bourg périurbain",
    "marcheImmobilier": "intermédiaire",
    "tauxMaisonLabel": "majoritairement pavillonnaire"
  },
  {
    "nom": "Val de Virvée",
    "slug": "val-de-virvee",
    "codeInsee": "33018",
    "codePostal": "33240",
    "population": 3793,
    "latitude": 45.021,
    "longitude": -0.3887,
    "altitude": 26,
    "logements": 1724,
    "logementsMaison": 66,
    "prixM2Moyen": 2830,
    "vehiculesElectriques": 145,
    "croissanceVE": 32,
    "bornesPubliques": 8,
    "intercommunalite": "Communauté de Communes des Portes de l'Entre-deux-Mers",
    "canton": "Val de Virvée",
    "distanceBordeaux": 25.3,
    "densiteBornes": 2.1,
    "profilCommune": "bourg périurbain",
    "marcheImmobilier": "accessible",
    "tauxMaisonLabel": "majoritairement pavillonnaire"
  },
  {
    "nom": "Saint-Selve",
    "slug": "saint-selve",
    "codeInsee": "33474",
    "codePostal": "33650",
    "population": 3746,
    "latitude": 44.6574,
    "longitude": -0.4726,
    "altitude": 17,
    "logements": 1703,
    "logementsMaison": 57,
    "prixM2Moyen": 3260,
    "vehiculesElectriques": 146,
    "croissanceVE": 26,
    "bornesPubliques": 8,
    "intercommunalite": "Communauté de Communes des Portes de l'Entre-deux-Mers",
    "canton": "Saint-Selve",
    "distanceBordeaux": 21.8,
    "densiteBornes": 2.1,
    "profilCommune": "bourg périurbain",
    "marcheImmobilier": "intermédiaire",
    "tauxMaisonLabel": "mixte pavillonnaire-collectif"
  },
  {
    "nom": "Latresne",
    "slug": "latresne",
    "codeInsee": "33234",
    "codePostal": "33360",
    "population": 3714,
    "latitude": 44.7901,
    "longitude": -0.4981,
    "altitude": 25,
    "logements": 1688,
    "logementsMaison": 65,
    "prixM2Moyen": 3190,
    "vehiculesElectriques": 156,
    "croissanceVE": 21,
    "bornesPubliques": 5,
    "intercommunalite": "Communauté de Communes des Portes de l'Entre-deux-Mers",
    "canton": "Latresne",
    "distanceBordeaux": 8.3,
    "densiteBornes": 1.3,
    "profilCommune": "bourg périurbain",
    "marcheImmobilier": "accessible",
    "tauxMaisonLabel": "majoritairement pavillonnaire"
  },
  {
    "nom": "Martillac",
    "slug": "martillac",
    "codeInsee": "33274",
    "codePostal": "33650",
    "population": 3659,
    "latitude": 44.7176,
    "longitude": -0.558,
    "altitude": 18,
    "logements": 1663,
    "logementsMaison": 58,
    "prixM2Moyen": 3350,
    "vehiculesElectriques": 138,
    "croissanceVE": 18,
    "bornesPubliques": 8,
    "intercommunalite": "Communauté de Communes des Portes de l'Entre-deux-Mers",
    "canton": "Martillac",
    "distanceBordeaux": 13.5,
    "densiteBornes": 2.2,
    "profilCommune": "bourg périurbain",
    "marcheImmobilier": "intermédiaire",
    "tauxMaisonLabel": "mixte pavillonnaire-collectif"
  },
  {
    "nom": "Montussan",
    "slug": "montussan",
    "codeInsee": "33293",
    "codePostal": "33450",
    "population": 3628,
    "latitude": 44.8843,
    "longitude": -0.4294,
    "altitude": 15,
    "logements": 1649,
    "logementsMaison": 55,
    "prixM2Moyen": 3520,
    "vehiculesElectriques": 142,
    "croissanceVE": 29,
    "bornesPubliques": 5,
    "intercommunalite": "Communauté de Communes des Portes de l'Entre-deux-Mers",
    "canton": "Montussan",
    "distanceBordeaux": 12.9,
    "densiteBornes": 1.4,
    "profilCommune": "bourg périurbain",
    "marcheImmobilier": "intermédiaire",
    "tauxMaisonLabel": "mixte pavillonnaire-collectif"
  },
  {
    "nom": "Saint-Savin",
    "slug": "saint-savin",
    "codeInsee": "33473",
    "codePostal": "33920",
    "population": 3582,
    "latitude": 45.1611,
    "longitude": -0.4449,
    "altitude": 15,
    "logements": 1628,
    "logementsMaison": 55,
    "prixM2Moyen": 3550,
    "vehiculesElectriques": 145,
    "croissanceVE": 30,
    "bornesPubliques": 10,
    "intercommunalite": "Communauté de Communes des Portes de l'Entre-deux-Mers",
    "canton": "Saint-Savin",
    "distanceBordeaux": 37.5,
    "densiteBornes": 2.8,
    "profilCommune": "bourg périurbain",
    "marcheImmobilier": "intermédiaire",
    "tauxMaisonLabel": "mixte pavillonnaire-collectif"
  },
  {
    "nom": "Pompignac",
    "slug": "pompignac",
    "codeInsee": "33330",
    "codePostal": "33370",
    "population": 3577,
    "latitude": 44.8527,
    "longitude": -0.4347,
    "altitude": 23,
    "logements": 1626,
    "logementsMaison": 63,
    "prixM2Moyen": 2870,
    "vehiculesElectriques": 166,
    "croissanceVE": 29,
    "bornesPubliques": 7,
    "intercommunalite": "Bordeaux Métropole",
    "canton": "Pompignac",
    "distanceBordeaux": 11.5,
    "densiteBornes": 2,
    "profilCommune": "bourg périurbain",
    "marcheImmobilier": "accessible",
    "tauxMaisonLabel": "majoritairement pavillonnaire"
  },
  {
    "nom": "Saucats",
    "slug": "saucats",
    "codeInsee": "33501",
    "codePostal": "33650",
    "population": 3548,
    "latitude": 44.6476,
    "longitude": -0.6377,
    "altitude": 24,
    "logements": 1613,
    "logementsMaison": 64,
    "prixM2Moyen": 2810,
    "vehiculesElectriques": 154,
    "croissanceVE": 33,
    "bornesPubliques": 4,
    "intercommunalite": "Communauté de Communes des Portes de l'Entre-deux-Mers",
    "canton": "Saucats",
    "distanceBordeaux": 21.6,
    "densiteBornes": 1.1,
    "profilCommune": "bourg périurbain",
    "marcheImmobilier": "accessible",
    "tauxMaisonLabel": "majoritairement pavillonnaire"
  },
  {
    "nom": "Fargues-Saint-Hilaire",
    "slug": "fargues-saint-hilaire",
    "codeInsee": "33165",
    "codePostal": "33370",
    "population": 3543,
    "latitude": 44.8202,
    "longitude": -0.4399,
    "altitude": 17,
    "logements": 1610,
    "logementsMaison": 57,
    "prixM2Moyen": 3120,
    "vehiculesElectriques": 121,
    "croissanceVE": 23,
    "bornesPubliques": 8,
    "intercommunalite": "Bordeaux Métropole",
    "canton": "Fargues-Saint-Hilaire",
    "distanceBordeaux": 11.2,
    "densiteBornes": 2.3,
    "profilCommune": "bourg périurbain",
    "marcheImmobilier": "accessible",
    "tauxMaisonLabel": "mixte pavillonnaire-collectif"
  },
  {
    "nom": "Le Porge",
    "slug": "le-porge",
    "codeInsee": "33333",
    "codePostal": "33680",
    "population": 3465,
    "latitude": 44.8649,
    "longitude": -1.1351,
    "altitude": 18,
    "logements": 1575,
    "logementsMaison": 87,
    "prixM2Moyen": 3080,
    "vehiculesElectriques": 153,
    "croissanceVE": 20,
    "bornesPubliques": 9,
    "intercommunalite": "Communauté de Communes des Portes de l'Entre-deux-Mers",
    "canton": "Le Porge",
    "distanceBordeaux": 43.9,
    "densiteBornes": 2.6,
    "profilCommune": "bourg périurbain",
    "marcheImmobilier": "accessible",
    "tauxMaisonLabel": "très pavillonnaire"
  },
  {
    "nom": "Saint-Caprais-de-Bordeaux",
    "slug": "saint-caprais-de-bordeaux",
    "codeInsee": "33381",
    "codePostal": "33880",
    "population": 3450,
    "latitude": 44.7544,
    "longitude": -0.4262,
    "altitude": 23,
    "logements": 1568,
    "logementsMaison": 63,
    "prixM2Moyen": 2960,
    "vehiculesElectriques": 149,
    "croissanceVE": 25,
    "bornesPubliques": 6,
    "intercommunalite": "Communauté de Communes des Portes de l'Entre-deux-Mers",
    "canton": "Saint-Caprais-de-Bordeaux",
    "distanceBordeaux": 15.2,
    "densiteBornes": 1.7,
    "profilCommune": "bourg périurbain",
    "marcheImmobilier": "accessible",
    "tauxMaisonLabel": "majoritairement pavillonnaire"
  },
  {
    "nom": "Saint-Médard-d'Eyrans",
    "slug": "saint-medard-d-eyrans",
    "codeInsee": "33448",
    "codePostal": "33650",
    "population": 3409,
    "latitude": 44.714,
    "longitude": -0.5125,
    "altitude": 15,
    "logements": 1550,
    "logementsMaison": 55,
    "prixM2Moyen": 3620,
    "vehiculesElectriques": 142,
    "croissanceVE": 28,
    "bornesPubliques": 7,
    "intercommunalite": "Communauté de Communes des Portes de l'Entre-deux-Mers",
    "canton": "Saint-Médard-d'Eyrans",
    "distanceBordeaux": 14.7,
    "densiteBornes": 2.1,
    "profilCommune": "bourg périurbain",
    "marcheImmobilier": "intermédiaire",
    "tauxMaisonLabel": "mixte pavillonnaire-collectif"
  },
  {
    "nom": "Castillon-la-Bataille",
    "slug": "castillon-la-bataille",
    "codeInsee": "33108",
    "codePostal": "33350",
    "population": 3344,
    "latitude": 44.8622,
    "longitude": -0.0244,
    "altitude": 68,
    "logements": 1520,
    "logementsMaison": 88,
    "prixM2Moyen": 3620,
    "vehiculesElectriques": 158,
    "croissanceVE": 27,
    "bornesPubliques": 8,
    "intercommunalite": "Communauté de Communes des Portes de l'Entre-deux-Mers",
    "canton": "Castillon-la-Bataille",
    "distanceBordeaux": 43.8,
    "densiteBornes": 2.4,
    "profilCommune": "bourg périurbain",
    "marcheImmobilier": "intermédiaire",
    "tauxMaisonLabel": "très pavillonnaire"
  },
  {
    "nom": "Ambès",
    "slug": "ambes",
    "codeInsee": "33004",
    "codePostal": "33810",
    "population": 3313,
    "latitude": 45.0123,
    "longitude": -0.5486,
    "altitude": 16,
    "logements": 1506,
    "logementsMaison": 56,
    "prixM2Moyen": 2990,
    "vehiculesElectriques": 111,
    "croissanceVE": 19,
    "bornesPubliques": 4,
    "intercommunalite": "Communauté de Communes des Portes de l'Entre-deux-Mers",
    "canton": "Ambès",
    "distanceBordeaux": 19.6,
    "densiteBornes": 1.2,
    "profilCommune": "bourg périurbain",
    "marcheImmobilier": "accessible",
    "tauxMaisonLabel": "mixte pavillonnaire-collectif"
  },
  {
    "nom": "Podensac",
    "slug": "podensac",
    "codeInsee": "33327",
    "codePostal": "33720",
    "population": 3269,
    "latitude": 44.6479,
    "longitude": -0.3576,
    "altitude": 21,
    "logements": 1486,
    "logementsMaison": 61,
    "prixM2Moyen": 3310,
    "vehiculesElectriques": 116,
    "croissanceVE": 30,
    "bornesPubliques": 7,
    "intercommunalite": "Communauté de Communes des Portes de l'Entre-deux-Mers",
    "canton": "Podensac",
    "distanceBordeaux": 27.4,
    "densiteBornes": 2.1,
    "profilCommune": "bourg périurbain",
    "marcheImmobilier": "intermédiaire",
    "tauxMaisonLabel": "majoritairement pavillonnaire"
  },
  {
    "nom": "Camblanes-et-Meynac",
    "slug": "camblanes-et-meynac",
    "codeInsee": "33085",
    "codePostal": "33360",
    "population": 3181,
    "latitude": 44.7643,
    "longitude": -0.474,
    "altitude": 25,
    "logements": 1446,
    "logementsMaison": 65,
    "prixM2Moyen": 3480,
    "vehiculesElectriques": 152,
    "croissanceVE": 33,
    "bornesPubliques": 6,
    "intercommunalite": "Communauté de Communes des Portes de l'Entre-deux-Mers",
    "canton": "Camblanes-et-Meynac",
    "distanceBordeaux": 11.6,
    "densiteBornes": 1.9,
    "profilCommune": "bourg périurbain",
    "marcheImmobilier": "intermédiaire",
    "tauxMaisonLabel": "majoritairement pavillonnaire"
  },
  {
    "nom": "Saint-Ciers-sur-Gironde",
    "slug": "saint-ciers-sur-gironde",
    "codeInsee": "33389",
    "codePostal": "33820",
    "population": 3175,
    "latitude": 45.2947,
    "longitude": -0.6648,
    "altitude": 16,
    "logements": 1443,
    "logementsMaison": 56,
    "prixM2Moyen": 3060,
    "vehiculesElectriques": 145,
    "croissanceVE": 23,
    "bornesPubliques": 8,
    "intercommunalite": "Communauté de Communes des Portes de l'Entre-deux-Mers",
    "canton": "Saint-Ciers-sur-Gironde",
    "distanceBordeaux": 51.2,
    "densiteBornes": 2.5,
    "profilCommune": "bourg périurbain",
    "marcheImmobilier": "accessible",
    "tauxMaisonLabel": "mixte pavillonnaire-collectif"
  },
  {
    "nom": "Saint-Seurin-sur-l'Isle",
    "slug": "saint-seurin-sur-l-isle",
    "codeInsee": "33478",
    "codePostal": "33660",
    "population": 3167,
    "latitude": 45.0093,
    "longitude": -0.004,
    "altitude": 66,
    "logements": 1440,
    "logementsMaison": 82,
    "prixM2Moyen": 3640,
    "vehiculesElectriques": 159,
    "croissanceVE": 25,
    "bornesPubliques": 6,
    "intercommunalite": "Communauté d'Agglomération du Libournais (La CALI)",
    "canton": "Saint-Seurin-sur-l'Isle",
    "distanceBordeaux": 49.1,
    "densiteBornes": 1.9,
    "profilCommune": "bourg périurbain",
    "marcheImmobilier": "intermédiaire",
    "tauxMaisonLabel": "très pavillonnaire"
  },
  {
    "nom": "Galgon",
    "slug": "galgon",
    "codeInsee": "33179",
    "codePostal": "33133",
    "population": 3144,
    "latitude": 44.991,
    "longitude": -0.278,
    "altitude": 67,
    "logements": 1429,
    "logementsMaison": 84,
    "prixM2Moyen": 3360,
    "vehiculesElectriques": 152,
    "croissanceVE": 27,
    "bornesPubliques": 4,
    "intercommunalite": "Communauté de Communes des Portes de l'Entre-deux-Mers",
    "canton": "Galgon",
    "distanceBordeaux": 29.2,
    "densiteBornes": 1.3,
    "profilCommune": "bourg périurbain",
    "marcheImmobilier": "intermédiaire",
    "tauxMaisonLabel": "très pavillonnaire"
  },
  {
    "nom": "Avensan",
    "slug": "avensan",
    "codeInsee": "33022",
    "codePostal": "33480",
    "population": 3140,
    "latitude": 45.0033,
    "longitude": -0.7574,
    "altitude": 26,
    "logements": 1427,
    "logementsMaison": 66,
    "prixM2Moyen": 3560,
    "vehiculesElectriques": 124,
    "croissanceVE": 21,
    "bornesPubliques": 6,
    "intercommunalite": "Communauté de Communes des Portes de l'Entre-deux-Mers",
    "canton": "Avensan",
    "distanceBordeaux": 23.1,
    "densiteBornes": 1.9,
    "profilCommune": "bourg périurbain",
    "marcheImmobilier": "intermédiaire",
    "tauxMaisonLabel": "majoritairement pavillonnaire"
  },
  {
    "nom": "Soulac-sur-Mer",
    "slug": "soulac-sur-mer",
    "codeInsee": "33514",
    "codePostal": "33780",
    "population": 3100,
    "latitude": 45.5057,
    "longitude": -1.0694,
    "altitude": 15,
    "logements": 1409,
    "logementsMaison": 89,
    "prixM2Moyen": 3410,
    "vehiculesElectriques": 133,
    "croissanceVE": 24,
    "bornesPubliques": 5,
    "intercommunalite": "Communauté de Communes des Portes de l'Entre-deux-Mers",
    "canton": "Soulac-sur-Mer",
    "distanceBordeaux": 83.6,
    "densiteBornes": 1.6,
    "profilCommune": "bourg périurbain",
    "marcheImmobilier": "intermédiaire",
    "tauxMaisonLabel": "très pavillonnaire"
  },
  {
    "nom": "Sainte-Hélène",
    "slug": "sainte-helene",
    "codeInsee": "33417",
    "codePostal": "33480",
    "population": 3091,
    "latitude": 44.9653,
    "longitude": -0.9071,
    "altitude": 13,
    "logements": 1405,
    "logementsMaison": 82,
    "prixM2Moyen": 3500,
    "vehiculesElectriques": 156,
    "croissanceVE": 19,
    "bornesPubliques": 8,
    "intercommunalite": "Communauté de Communes des Portes de l'Entre-deux-Mers",
    "canton": "Sainte-Hélène",
    "distanceBordeaux": 29.5,
    "densiteBornes": 2.6,
    "profilCommune": "bourg périurbain",
    "marcheImmobilier": "intermédiaire",
    "tauxMaisonLabel": "très pavillonnaire"
  },
  {
    "nom": "Yvrac",
    "slug": "yvrac",
    "codeInsee": "33554",
    "codePostal": "33370",
    "population": 2899,
    "latitude": 44.8817,
    "longitude": -0.4705,
    "altitude": 15,
    "logements": 1318,
    "logementsMaison": 55,
    "prixM2Moyen": 3200,
    "vehiculesElectriques": 100,
    "croissanceVE": 32,
    "bornesPubliques": 9,
    "intercommunalite": "Bordeaux Métropole",
    "canton": "Yvrac",
    "distanceBordeaux": 9.9,
    "densiteBornes": 3.1,
    "profilCommune": "bourg périurbain",
    "marcheImmobilier": "intermédiaire",
    "tauxMaisonLabel": "mixte pavillonnaire-collectif"
  },
  {
    "nom": "Toulenne",
    "slug": "toulenne",
    "codeInsee": "33533",
    "codePostal": "33210",
    "population": 2881,
    "latitude": 44.5665,
    "longitude": -0.2735,
    "altitude": 73,
    "logements": 1310,
    "logementsMaison": 86,
    "prixM2Moyen": 3200,
    "vehiculesElectriques": 151,
    "croissanceVE": 27,
    "bornesPubliques": 4,
    "intercommunalite": "Communauté de Communes du Sud Gironde",
    "canton": "Toulenne",
    "distanceBordeaux": 38.6,
    "densiteBornes": 1.4,
    "profilCommune": "bourg périurbain",
    "marcheImmobilier": "intermédiaire",
    "tauxMaisonLabel": "très pavillonnaire"
  },
  {
    "nom": "Margaux-Cantenac",
    "slug": "margaux-cantenac",
    "codeInsee": "33268",
    "codePostal": "33460",
    "population": 2845,
    "latitude": 45.0363,
    "longitude": -0.6788,
    "altitude": 27,
    "logements": 1293,
    "logementsMaison": 67,
    "prixM2Moyen": 3120,
    "vehiculesElectriques": 136,
    "croissanceVE": 24,
    "bornesPubliques": 7,
    "intercommunalite": "Communauté de Communes Médoc Estuaire",
    "canton": "Margaux-Cantenac",
    "distanceBordeaux": 23.4,
    "densiteBornes": 2.5,
    "profilCommune": "bourg périurbain",
    "marcheImmobilier": "accessible",
    "tauxMaisonLabel": "majoritairement pavillonnaire"
  },
  {
    "nom": "Vendays-Montalivet",
    "slug": "vendays-montalivet",
    "codeInsee": "33540",
    "codePostal": "33930",
    "population": 2838,
    "latitude": 45.3378,
    "longitude": -1.0953,
    "altitude": 16,
    "logements": 1290,
    "logementsMaison": 86,
    "prixM2Moyen": 3050,
    "vehiculesElectriques": 146,
    "croissanceVE": 23,
    "bornesPubliques": 4,
    "intercommunalite": "Communauté de Communes des Portes de l'Entre-deux-Mers",
    "canton": "Vendays-Montalivet",
    "distanceBordeaux": 68.8,
    "densiteBornes": 1.4,
    "profilCommune": "bourg périurbain",
    "marcheImmobilier": "accessible",
    "tauxMaisonLabel": "très pavillonnaire"
  },
  {
    "nom": "Laruscade",
    "slug": "laruscade",
    "codeInsee": "33233",
    "codePostal": "33620",
    "population": 2811,
    "latitude": 45.1206,
    "longitude": -0.3394,
    "altitude": 26,
    "logements": 1278,
    "logementsMaison": 66,
    "prixM2Moyen": 3220,
    "vehiculesElectriques": 114,
    "croissanceVE": 23,
    "bornesPubliques": 6,
    "intercommunalite": "Communauté de Communes des Portes de l'Entre-deux-Mers",
    "canton": "Laruscade",
    "distanceBordeaux": 36.7,
    "densiteBornes": 2.1,
    "profilCommune": "bourg périurbain",
    "marcheImmobilier": "intermédiaire",
    "tauxMaisonLabel": "majoritairement pavillonnaire"
  },
  {
    "nom": "Listrac-Médoc",
    "slug": "listrac-medoc",
    "codeInsee": "33248",
    "codePostal": "33480",
    "population": 2807,
    "latitude": 45.0699,
    "longitude": -0.827,
    "altitude": 8,
    "logements": 1276,
    "logementsMaison": 87,
    "prixM2Moyen": 2900,
    "vehiculesElectriques": 141,
    "croissanceVE": 30,
    "bornesPubliques": 9,
    "intercommunalite": "Communauté de Communes des Portes de l'Entre-deux-Mers",
    "canton": "Listrac-Médoc",
    "distanceBordeaux": 32.3,
    "densiteBornes": 3.2,
    "profilCommune": "bourg périurbain",
    "marcheImmobilier": "accessible",
    "tauxMaisonLabel": "très pavillonnaire"
  },
  {
    "nom": "Sallebœuf",
    "slug": "sallebuf",
    "codeInsee": "33496",
    "codePostal": "33370",
    "population": 2767,
    "latitude": 44.8423,
    "longitude": -0.392,
    "altitude": 24,
    "logements": 1258,
    "logementsMaison": 64,
    "prixM2Moyen": 3410,
    "vehiculesElectriques": 101,
    "croissanceVE": 19,
    "bornesPubliques": 4,
    "intercommunalite": "Bordeaux Métropole",
    "canton": "Sallebœuf",
    "distanceBordeaux": 14.8,
    "densiteBornes": 1.4,
    "profilCommune": "bourg périurbain",
    "marcheImmobilier": "intermédiaire",
    "tauxMaisonLabel": "majoritairement pavillonnaire"
  },
  {
    "nom": "La Lande-de-Fronsac",
    "slug": "la-lande-de-fronsac",
    "codeInsee": "33219",
    "codePostal": "33240",
    "population": 2729,
    "latitude": 44.9849,
    "longitude": -0.3797,
    "altitude": 24,
    "logements": 1240,
    "logementsMaison": 64,
    "prixM2Moyen": 3410,
    "vehiculesElectriques": 133,
    "croissanceVE": 22,
    "bornesPubliques": 9,
    "intercommunalite": "Communauté de Communes des Portes de l'Entre-deux-Mers",
    "canton": "La Lande-de-Fronsac",
    "distanceBordeaux": 22.7,
    "densiteBornes": 3.3,
    "profilCommune": "bourg périurbain",
    "marcheImmobilier": "intermédiaire",
    "tauxMaisonLabel": "majoritairement pavillonnaire"
  },
  {
    "nom": "Cézac",
    "slug": "cezac",
    "codeInsee": "33123",
    "codePostal": "33620",
    "population": 2727,
    "latitude": 45.0867,
    "longitude": -0.4171,
    "altitude": 29,
    "logements": 1240,
    "logementsMaison": 69,
    "prixM2Moyen": 3480,
    "vehiculesElectriques": 108,
    "croissanceVE": 29,
    "bornesPubliques": 8,
    "intercommunalite": "Communauté de Communes des Portes de l'Entre-deux-Mers",
    "canton": "Cézac",
    "distanceBordeaux": 30.5,
    "densiteBornes": 2.9,
    "profilCommune": "bourg périurbain",
    "marcheImmobilier": "intermédiaire",
    "tauxMaisonLabel": "majoritairement pavillonnaire"
  },
  {
    "nom": "Saint-Quentin-de-Baron",
    "slug": "saint-quentin-de-baron",
    "codeInsee": "33466",
    "codePostal": "33750",
    "population": 2713,
    "latitude": 44.8175,
    "longitude": -0.2811,
    "altitude": 73,
    "logements": 1233,
    "logementsMaison": 87,
    "prixM2Moyen": 3110,
    "vehiculesElectriques": 117,
    "croissanceVE": 26,
    "bornesPubliques": 7,
    "intercommunalite": "Communauté de Communes des Portes de l'Entre-deux-Mers",
    "canton": "Saint-Quentin-de-Baron",
    "distanceBordeaux": 23.6,
    "densiteBornes": 2.6,
    "profilCommune": "bourg périurbain",
    "marcheImmobilier": "accessible",
    "tauxMaisonLabel": "très pavillonnaire"
  },
  {
    "nom": "Castres-Gironde",
    "slug": "castres-gironde",
    "codeInsee": "33109",
    "codePostal": "33640",
    "population": 2695,
    "latitude": 44.6866,
    "longitude": -0.4566,
    "altitude": 24,
    "logements": 1225,
    "logementsMaison": 64,
    "prixM2Moyen": 3610,
    "vehiculesElectriques": 100,
    "croissanceVE": 33,
    "bornesPubliques": 6,
    "intercommunalite": "Communauté de Communes des Portes de l'Entre-deux-Mers",
    "canton": "Castres-Gironde",
    "distanceBordeaux": 19.4,
    "densiteBornes": 2.2,
    "profilCommune": "bourg périurbain",
    "marcheImmobilier": "intermédiaire",
    "tauxMaisonLabel": "majoritairement pavillonnaire"
  },
  {
    "nom": "Cubzac-les-Ponts",
    "slug": "cubzac-les-ponts",
    "codeInsee": "33143",
    "codePostal": "33240",
    "population": 2693,
    "latitude": 44.9674,
    "longitude": -0.4426,
    "altitude": 20,
    "logements": 1224,
    "logementsMaison": 60,
    "prixM2Moyen": 2980,
    "vehiculesElectriques": 105,
    "croissanceVE": 19,
    "bornesPubliques": 8,
    "intercommunalite": "Communauté de Communes des Portes de l'Entre-deux-Mers",
    "canton": "Cubzac-les-Ponts",
    "distanceBordeaux": 18,
    "densiteBornes": 3,
    "profilCommune": "bourg périurbain",
    "marcheImmobilier": "accessible",
    "tauxMaisonLabel": "majoritairement pavillonnaire"
  },
  {
    "nom": "Cadillac-sur-Garonne",
    "slug": "cadillac-sur-garonne",
    "codeInsee": "33081",
    "codePostal": "33410",
    "population": 2670,
    "latitude": 44.6407,
    "longitude": -0.3076,
    "altitude": 17,
    "logements": 1214,
    "logementsMaison": 57,
    "prixM2Moyen": 3320,
    "vehiculesElectriques": 127,
    "croissanceVE": 20,
    "bornesPubliques": 7,
    "intercommunalite": "Communauté de Communes des Portes de l'Entre-deux-Mers",
    "canton": "Cadillac-sur-Garonne",
    "distanceBordeaux": 30.7,
    "densiteBornes": 2.6,
    "profilCommune": "bourg périurbain",
    "marcheImmobilier": "intermédiaire",
    "tauxMaisonLabel": "mixte pavillonnaire-collectif"
  },
  {
    "nom": "Beychac-et-Caillau",
    "slug": "beychac-et-caillau",
    "codeInsee": "33049",
    "codePostal": "33750",
    "population": 2625,
    "latitude": 44.8708,
    "longitude": -0.3726,
    "altitude": 22,
    "logements": 1193,
    "logementsMaison": 62,
    "prixM2Moyen": 3230,
    "vehiculesElectriques": 110,
    "croissanceVE": 28,
    "bornesPubliques": 7,
    "intercommunalite": "Communauté de Communes des Portes de l'Entre-deux-Mers",
    "canton": "Beychac-et-Caillau",
    "distanceBordeaux": 16.7,
    "densiteBornes": 2.7,
    "profilCommune": "bourg périurbain",
    "marcheImmobilier": "intermédiaire",
    "tauxMaisonLabel": "majoritairement pavillonnaire"
  },
  {
    "nom": "Portets",
    "slug": "portets",
    "codeInsee": "33334",
    "codePostal": "33640",
    "population": 2618,
    "latitude": 44.6783,
    "longitude": -0.4263,
    "altitude": 22,
    "logements": 1190,
    "logementsMaison": 62,
    "prixM2Moyen": 3290,
    "vehiculesElectriques": 120,
    "croissanceVE": 20,
    "bornesPubliques": 7,
    "intercommunalite": "Communauté de Communes des Portes de l'Entre-deux-Mers",
    "canton": "Portets",
    "distanceBordeaux": 21.5,
    "densiteBornes": 2.7,
    "profilCommune": "bourg périurbain",
    "marcheImmobilier": "intermédiaire",
    "tauxMaisonLabel": "majoritairement pavillonnaire"
  },
  {
    "nom": "Saint-Yzan-de-Soudiac",
    "slug": "saint-yzan-de-soudiac",
    "codeInsee": "33492",
    "codePostal": "33920",
    "population": 2586,
    "latitude": 45.1548,
    "longitude": -0.4047,
    "altitude": 25,
    "logements": 1175,
    "logementsMaison": 65,
    "prixM2Moyen": 3130,
    "vehiculesElectriques": 120,
    "croissanceVE": 32,
    "bornesPubliques": 9,
    "intercommunalite": "Communauté de Communes des Portes de l'Entre-deux-Mers",
    "canton": "Saint-Yzan-de-Soudiac",
    "distanceBordeaux": 37.8,
    "densiteBornes": 3.5,
    "profilCommune": "bourg périurbain",
    "marcheImmobilier": "accessible",
    "tauxMaisonLabel": "majoritairement pavillonnaire"
  },
  {
    "nom": "Sainte-Foy-la-Grande",
    "slug": "sainte-foy-la-grande",
    "codeInsee": "33402",
    "codePostal": "33220",
    "population": 2507,
    "latitude": 44.8407,
    "longitude": 0.2171,
    "altitude": 62,
    "logements": 1140,
    "logementsMaison": 87,
    "prixM2Moyen": 2960,
    "vehiculesElectriques": 127,
    "croissanceVE": 18,
    "bornesPubliques": 7,
    "intercommunalite": "Communauté de Communes des Portes de l'Entre-deux-Mers",
    "canton": "Sainte-Foy-la-Grande",
    "distanceBordeaux": 62.8,
    "densiteBornes": 2.8,
    "profilCommune": "bourg périurbain",
    "marcheImmobilier": "accessible",
    "tauxMaisonLabel": "très pavillonnaire"
  },
  {
    "nom": "Beautiran",
    "slug": "beautiran",
    "codeInsee": "33037",
    "codePostal": "33640",
    "population": 2488,
    "latitude": 44.7035,
    "longitude": -0.4604,
    "altitude": 29,
    "logements": 1131,
    "logementsMaison": 69,
    "prixM2Moyen": 2840,
    "vehiculesElectriques": 99,
    "croissanceVE": 20,
    "bornesPubliques": 5,
    "intercommunalite": "Communauté de Communes des Portes de l'Entre-deux-Mers",
    "canton": "Beautiran",
    "distanceBordeaux": 17.6,
    "densiteBornes": 2,
    "profilCommune": "bourg périurbain",
    "marcheImmobilier": "accessible",
    "tauxMaisonLabel": "majoritairement pavillonnaire"
  },
  {
    "nom": "Pugnac",
    "slug": "pugnac",
    "codeInsee": "33341",
    "codePostal": "33710",
    "population": 2453,
    "latitude": 45.0825,
    "longitude": -0.5003,
    "altitude": 16,
    "logements": 1115,
    "logementsMaison": 56,
    "prixM2Moyen": 3160,
    "vehiculesElectriques": 93,
    "croissanceVE": 21,
    "bornesPubliques": 4,
    "intercommunalite": "Communauté de Communes des Portes de l'Entre-deux-Mers",
    "canton": "Pugnac",
    "distanceBordeaux": 27.9,
    "densiteBornes": 1.6,
    "profilCommune": "bourg périurbain",
    "marcheImmobilier": "accessible",
    "tauxMaisonLabel": "mixte pavillonnaire-collectif"
  },
  {
    "nom": "Saint-Médard-de-Guizières",
    "slug": "saint-medard-de-guizieres",
    "codeInsee": "33447",
    "codePostal": "33230",
    "population": 2438,
    "latitude": 45.0111,
    "longitude": -0.0729,
    "altitude": 64,
    "logements": 1108,
    "logementsMaison": 83,
    "prixM2Moyen": 3130,
    "vehiculesElectriques": 115,
    "croissanceVE": 20,
    "bornesPubliques": 9,
    "intercommunalite": "Communauté d'Agglomération du Libournais (La CALI)",
    "canton": "Saint-Médard-de-Guizières",
    "distanceBordeaux": 44.3,
    "densiteBornes": 3.7,
    "profilCommune": "bourg périurbain",
    "marcheImmobilier": "accessible",
    "tauxMaisonLabel": "très pavillonnaire"
  },
  {
    "nom": "Carcans",
    "slug": "carcans",
    "codeInsee": "33097",
    "codePostal": "33121",
    "population": 2415,
    "latitude": 45.0794,
    "longitude": -1.0404,
    "altitude": 7,
    "logements": 1098,
    "logementsMaison": 93,
    "prixM2Moyen": 3180,
    "vehiculesElectriques": 120,
    "croissanceVE": 20,
    "bornesPubliques": 5,
    "intercommunalite": "Communauté de Communes des Portes de l'Entre-deux-Mers",
    "canton": "Carcans",
    "distanceBordeaux": 45.2,
    "densiteBornes": 2.1,
    "profilCommune": "bourg périurbain",
    "marcheImmobilier": "accessible",
    "tauxMaisonLabel": "très pavillonnaire"
  },
  {
    "nom": "Cabanac-et-Villagrains",
    "slug": "cabanac-et-villagrains",
    "codeInsee": "33077",
    "codePostal": "33650",
    "population": 2400,
    "latitude": 44.5889,
    "longitude": -0.5412,
    "altitude": 29,
    "logements": 1091,
    "logementsMaison": 86,
    "prixM2Moyen": 3220,
    "vehiculesElectriques": 111,
    "croissanceVE": 25,
    "bornesPubliques": 8,
    "intercommunalite": "Communauté de Communes des Portes de l'Entre-deux-Mers",
    "canton": "Cabanac-et-Villagrains",
    "distanceBordeaux": 27.8,
    "densiteBornes": 3.3,
    "profilCommune": "bourg périurbain",
    "marcheImmobilier": "intermédiaire",
    "tauxMaisonLabel": "très pavillonnaire"
  },
  {
    "nom": "Gaillan-en-Médoc",
    "slug": "gaillan-en-medoc",
    "codeInsee": "33177",
    "codePostal": "33340",
    "population": 2385,
    "latitude": 45.3135,
    "longitude": -0.9946,
    "altitude": 16,
    "logements": 1084,
    "logementsMaison": 93,
    "prixM2Moyen": 3000,
    "vehiculesElectriques": 118,
    "croissanceVE": 32,
    "bornesPubliques": 9,
    "intercommunalite": "Communauté de Communes des Portes de l'Entre-deux-Mers",
    "canton": "Gaillan-en-Médoc",
    "distanceBordeaux": 62.1,
    "densiteBornes": 3.8,
    "profilCommune": "bourg périurbain",
    "marcheImmobilier": "accessible",
    "tauxMaisonLabel": "très pavillonnaire"
  },
  {
    "nom": "Cavignac",
    "slug": "cavignac",
    "codeInsee": "33114",
    "codePostal": "33620",
    "population": 2372,
    "latitude": 45.0981,
    "longitude": -0.3784,
    "altitude": 27,
    "logements": 1078,
    "logementsMaison": 67,
    "prixM2Moyen": 3300,
    "vehiculesElectriques": 97,
    "croissanceVE": 33,
    "bornesPubliques": 4,
    "intercommunalite": "Communauté de Communes des Portes de l'Entre-deux-Mers",
    "canton": "Cavignac",
    "distanceBordeaux": 33,
    "densiteBornes": 1.7,
    "profilCommune": "bourg périurbain",
    "marcheImmobilier": "intermédiaire",
    "tauxMaisonLabel": "majoritairement pavillonnaire"
  },
  {
    "nom": "Cissac-Médoc",
    "slug": "cissac-medoc",
    "codeInsee": "33125",
    "codePostal": "33250",
    "population": 2332,
    "latitude": 45.2149,
    "longitude": -0.8413,
    "altitude": 5,
    "logements": 1060,
    "logementsMaison": 89,
    "prixM2Moyen": 3510,
    "vehiculesElectriques": 123,
    "croissanceVE": 18,
    "bornesPubliques": 7,
    "intercommunalite": "Communauté de Communes Médoc Estuaire",
    "canton": "Cissac-Médoc",
    "distanceBordeaux": 46.7,
    "densiteBornes": 3,
    "profilCommune": "bourg périurbain",
    "marcheImmobilier": "intermédiaire",
    "tauxMaisonLabel": "très pavillonnaire"
  },
  {
    "nom": "Landiras",
    "slug": "landiras",
    "codeInsee": "33225",
    "codePostal": "33720",
    "population": 2310,
    "latitude": 44.5696,
    "longitude": -0.4333,
    "altitude": 24,
    "logements": 1050,
    "logementsMaison": 90,
    "prixM2Moyen": 2810,
    "vehiculesElectriques": 90,
    "croissanceVE": 23,
    "bornesPubliques": 8,
    "intercommunalite": "Communauté de Communes des Portes de l'Entre-deux-Mers",
    "canton": "Landiras",
    "distanceBordeaux": 32,
    "densiteBornes": 3.5,
    "profilCommune": "bourg périurbain",
    "marcheImmobilier": "accessible",
    "tauxMaisonLabel": "très pavillonnaire"
  },
  {
    "nom": "Saint-Germain-du-Puch",
    "slug": "saint-germain-du-puch",
    "codeInsee": "33413",
    "codePostal": "33750",
    "population": 2304,
    "latitude": 44.8529,
    "longitude": -0.3334,
    "altitude": 29,
    "logements": 1047,
    "logementsMaison": 69,
    "prixM2Moyen": 3280,
    "vehiculesElectriques": 100,
    "croissanceVE": 29,
    "bornesPubliques": 8,
    "intercommunalite": "Communauté de Communes des Portes de l'Entre-deux-Mers",
    "canton": "Saint-Germain-du-Puch",
    "distanceBordeaux": 19.4,
    "densiteBornes": 3.5,
    "profilCommune": "bourg périurbain",
    "marcheImmobilier": "intermédiaire",
    "tauxMaisonLabel": "majoritairement pavillonnaire"
  },
  {
    "nom": "Cussac-Fort-Médoc",
    "slug": "cussac-fort-medoc",
    "codeInsee": "33146",
    "codePostal": "33460",
    "population": 2279,
    "latitude": 45.1207,
    "longitude": -0.726,
    "altitude": 18,
    "logements": 1036,
    "logementsMaison": 58,
    "prixM2Moyen": 3450,
    "vehiculesElectriques": 81,
    "croissanceVE": 20,
    "bornesPubliques": 9,
    "intercommunalite": "Communauté de Communes Médoc Estuaire",
    "canton": "Cussac-Fort-Médoc",
    "distanceBordeaux": 33.5,
    "densiteBornes": 3.9,
    "profilCommune": "bourg périurbain",
    "marcheImmobilier": "intermédiaire",
    "tauxMaisonLabel": "mixte pavillonnaire-collectif"
  },
  {
    "nom": "Bourg",
    "slug": "bourg",
    "codeInsee": "33067",
    "codePostal": "33710",
    "population": 2244,
    "latitude": 45.0396,
    "longitude": -0.5484,
    "altitude": 24,
    "logements": 1020,
    "logementsMaison": 64,
    "prixM2Moyen": 3450,
    "vehiculesElectriques": 91,
    "croissanceVE": 26,
    "bornesPubliques": 9,
    "intercommunalite": "Communauté de Communes des Portes de l'Entre-deux-Mers",
    "canton": "Bourg",
    "distanceBordeaux": 22.6,
    "densiteBornes": 4,
    "profilCommune": "bourg périurbain",
    "marcheImmobilier": "intermédiaire",
    "tauxMaisonLabel": "majoritairement pavillonnaire"
  },
  {
    "nom": "Quinsac",
    "slug": "quinsac",
    "codeInsee": "33349",
    "codePostal": "33360",
    "population": 2217,
    "latitude": 44.751,
    "longitude": -0.4876,
    "altitude": 24,
    "logements": 1008,
    "logementsMaison": 64,
    "prixM2Moyen": 2840,
    "vehiculesElectriques": 99,
    "croissanceVE": 25,
    "bornesPubliques": 4,
    "intercommunalite": "Communauté de Communes des Portes de l'Entre-deux-Mers",
    "canton": "Quinsac",
    "distanceBordeaux": 12.1,
    "densiteBornes": 1.8,
    "profilCommune": "bourg périurbain",
    "marcheImmobilier": "accessible",
    "tauxMaisonLabel": "majoritairement pavillonnaire"
  },
  {
    "nom": "Langoiran",
    "slug": "langoiran",
    "codeInsee": "33226",
    "codePostal": "33550",
    "population": 2215,
    "latitude": 44.7071,
    "longitude": -0.3734,
    "altitude": 19,
    "logements": 1007,
    "logementsMaison": 59,
    "prixM2Moyen": 2990,
    "vehiculesElectriques": 91,
    "croissanceVE": 20,
    "bornesPubliques": 7,
    "intercommunalite": "Communauté de Communes des Portes de l'Entre-deux-Mers",
    "canton": "Langoiran",
    "distanceBordeaux": 21.8,
    "densiteBornes": 3.2,
    "profilCommune": "bourg périurbain",
    "marcheImmobilier": "accessible",
    "tauxMaisonLabel": "mixte pavillonnaire-collectif"
  },
  {
    "nom": "Les Églisottes-et-Chalaures",
    "slug": "les-eglisottes-et-chalaures",
    "codeInsee": "33154",
    "codePostal": "33230",
    "population": 2205,
    "latitude": 45.0946,
    "longitude": -0.0389,
    "altitude": 71,
    "logements": 1002,
    "logementsMaison": 87,
    "prixM2Moyen": 3490,
    "vehiculesElectriques": 99,
    "croissanceVE": 28,
    "bornesPubliques": 9,
    "intercommunalite": "Communauté d'Agglomération du Libournais (La CALI)",
    "canton": "Les Églisottes-et-Chalaures",
    "distanceBordeaux": 51.2,
    "densiteBornes": 4.1,
    "profilCommune": "bourg périurbain",
    "marcheImmobilier": "intermédiaire",
    "tauxMaisonLabel": "très pavillonnaire"
  },
  {
    "nom": "Cénac",
    "slug": "cenac",
    "codeInsee": "33118",
    "codePostal": "33360",
    "population": 2195,
    "latitude": 44.7849,
    "longitude": -0.4573,
    "altitude": 17,
    "logements": 998,
    "logementsMaison": 57,
    "prixM2Moyen": 3000,
    "vehiculesElectriques": 88,
    "croissanceVE": 25,
    "bornesPubliques": 8,
    "intercommunalite": "Communauté de Communes des Portes de l'Entre-deux-Mers",
    "canton": "Cénac",
    "distanceBordeaux": 11.3,
    "densiteBornes": 3.6,
    "profilCommune": "bourg périurbain",
    "marcheImmobilier": "accessible",
    "tauxMaisonLabel": "mixte pavillonnaire-collectif"
  },
  {
    "nom": "Peujard",
    "slug": "peujard",
    "codeInsee": "33321",
    "codePostal": "33240",
    "population": 2195,
    "latitude": 45.0472,
    "longitude": -0.4313,
    "altitude": 15,
    "logements": 998,
    "logementsMaison": 55,
    "prixM2Moyen": 3160,
    "vehiculesElectriques": 88,
    "croissanceVE": 30,
    "bornesPubliques": 5,
    "intercommunalite": "Communauté de Communes des Portes de l'Entre-deux-Mers",
    "canton": "Peujard",
    "distanceBordeaux": 26,
    "densiteBornes": 2.3,
    "profilCommune": "bourg périurbain",
    "marcheImmobilier": "accessible",
    "tauxMaisonLabel": "mixte pavillonnaire-collectif"
  },
  {
    "nom": "Saint-Magne-de-Castillon",
    "slug": "saint-magne-de-castillon",
    "codeInsee": "33437",
    "codePostal": "33350",
    "population": 2165,
    "latitude": 44.8542,
    "longitude": -0.0716,
    "altitude": 71,
    "logements": 984,
    "logementsMaison": 92,
    "prixM2Moyen": 3640,
    "vehiculesElectriques": 113,
    "croissanceVE": 33,
    "bornesPubliques": 4,
    "intercommunalite": "Communauté de Communes des Portes de l'Entre-deux-Mers",
    "canton": "Saint-Magne-de-Castillon",
    "distanceBordeaux": 40.1,
    "densiteBornes": 1.8,
    "profilCommune": "bourg périurbain",
    "marcheImmobilier": "intermédiaire",
    "tauxMaisonLabel": "très pavillonnaire"
  },
  {
    "nom": "Preignac",
    "slug": "preignac",
    "codeInsee": "33337",
    "codePostal": "33210",
    "population": 2135,
    "latitude": 44.5719,
    "longitude": -0.3106,
    "altitude": 20,
    "logements": 970,
    "logementsMaison": 83,
    "prixM2Moyen": 2950,
    "vehiculesElectriques": 100,
    "croissanceVE": 30,
    "bornesPubliques": 8,
    "intercommunalite": "Communauté de Communes du Sud Gironde",
    "canton": "Preignac",
    "distanceBordeaux": 36.4,
    "densiteBornes": 3.7,
    "profilCommune": "bourg périurbain",
    "marcheImmobilier": "accessible",
    "tauxMaisonLabel": "très pavillonnaire"
  },
  {
    "nom": "Cérons",
    "slug": "cerons",
    "codeInsee": "33120",
    "codePostal": "33720",
    "population": 2126,
    "latitude": 44.6268,
    "longitude": -0.3404,
    "altitude": 19,
    "logements": 966,
    "logementsMaison": 59,
    "prixM2Moyen": 3480,
    "vehiculesElectriques": 102,
    "croissanceVE": 27,
    "bornesPubliques": 3,
    "intercommunalite": "Communauté de Communes des Portes de l'Entre-deux-Mers",
    "canton": "Cérons",
    "distanceBordeaux": 30.1,
    "densiteBornes": 1.4,
    "profilCommune": "bourg périurbain",
    "marcheImmobilier": "intermédiaire",
    "tauxMaisonLabel": "mixte pavillonnaire-collectif"
  },
  {
    "nom": "Targon",
    "slug": "targon",
    "codeInsee": "33523",
    "codePostal": "33760",
    "population": 2079,
    "latitude": 44.7375,
    "longitude": -0.2691,
    "altitude": 63,
    "logements": 945,
    "logementsMaison": 85,
    "prixM2Moyen": 3450,
    "vehiculesElectriques": 112,
    "croissanceVE": 24,
    "bornesPubliques": 8,
    "intercommunalite": "Communauté de Communes des Portes de l'Entre-deux-Mers",
    "canton": "Targon",
    "distanceBordeaux": 26.9,
    "densiteBornes": 3.8,
    "profilCommune": "bourg périurbain",
    "marcheImmobilier": "intermédiaire",
    "tauxMaisonLabel": "très pavillonnaire"
  },
  {
    "nom": "Barsac",
    "slug": "barsac",
    "codeInsee": "33030",
    "codePostal": "33720",
    "population": 2058,
    "latitude": 44.6036,
    "longitude": -0.3259,
    "altitude": 19,
    "logements": 935,
    "logementsMaison": 59,
    "prixM2Moyen": 2890,
    "vehiculesElectriques": 94,
    "croissanceVE": 25,
    "bornesPubliques": 3,
    "intercommunalite": "Communauté de Communes des Portes de l'Entre-deux-Mers",
    "canton": "Barsac",
    "distanceBordeaux": 32.8,
    "densiteBornes": 1.5,
    "profilCommune": "bourg périurbain",
    "marcheImmobilier": "accessible",
    "tauxMaisonLabel": "mixte pavillonnaire-collectif"
  },
  {
    "nom": "Saint-Maixant",
    "slug": "saint-maixant",
    "codeInsee": "33438",
    "codePostal": "33490",
    "population": 2057,
    "latitude": 44.5815,
    "longitude": -0.2481,
    "altitude": 66,
    "logements": 935,
    "logementsMaison": 84,
    "prixM2Moyen": 3420,
    "vehiculesElectriques": 89,
    "croissanceVE": 31,
    "bornesPubliques": 7,
    "intercommunalite": "Communauté de Communes des Portes de l'Entre-deux-Mers",
    "canton": "Saint-Maixant",
    "distanceBordeaux": 38.7,
    "densiteBornes": 3.4,
    "profilCommune": "bourg périurbain",
    "marcheImmobilier": "intermédiaire",
    "tauxMaisonLabel": "très pavillonnaire"
  },
  {
    "nom": "Arveyres",
    "slug": "arveyres",
    "codeInsee": "33015",
    "codePostal": "33500",
    "population": 2056,
    "latitude": 44.89,
    "longitude": -0.2798,
    "altitude": 66,
    "logements": 935,
    "logementsMaison": 87,
    "prixM2Moyen": 3200,
    "vehiculesElectriques": 87,
    "croissanceVE": 22,
    "bornesPubliques": 4,
    "intercommunalite": "Communauté d'Agglomération du Libournais (La CALI)",
    "canton": "Libourne",
    "distanceBordeaux": 24.3,
    "densiteBornes": 1.9,
    "profilCommune": "bourg périurbain",
    "marcheImmobilier": "intermédiaire",
    "tauxMaisonLabel": "très pavillonnaire"
  },
  {
    "nom": "Saint-Louis-de-Montferrand",
    "slug": "saint-louis-de-montferrand",
    "codeInsee": "33434",
    "codePostal": "33440",
    "population": 2051,
    "latitude": 44.957,
    "longitude": -0.5335,
    "altitude": 17,
    "logements": 932,
    "logementsMaison": 57,
    "prixM2Moyen": 2940,
    "vehiculesElectriques": 75,
    "croissanceVE": 24,
    "bornesPubliques": 8,
    "intercommunalite": "Bordeaux Métropole",
    "canton": "Saint-Louis-de-Montferrand",
    "distanceBordeaux": 13.7,
    "densiteBornes": 3.9,
    "profilCommune": "bourg périurbain",
    "marcheImmobilier": "accessible",
    "tauxMaisonLabel": "mixte pavillonnaire-collectif"
  },
  {
    "nom": "Abzac",
    "slug": "abzac",
    "codeInsee": "33001",
    "codePostal": "33230",
    "population": 2048,
    "latitude": 45.0123,
    "longitude": -0.1281,
    "altitude": 69,
    "logements": 931,
    "logementsMaison": 87,
    "prixM2Moyen": 3370,
    "vehiculesElectriques": 94,
    "croissanceVE": 28,
    "bornesPubliques": 8,
    "intercommunalite": "Communauté d'Agglomération du Libournais (La CALI)",
    "canton": "Abzac",
    "distanceBordeaux": 40.5,
    "densiteBornes": 3.9,
    "profilCommune": "bourg périurbain",
    "marcheImmobilier": "intermédiaire",
    "tauxMaisonLabel": "très pavillonnaire"
  },
  {
    "nom": "Génissac",
    "slug": "genissac",
    "codeInsee": "33185",
    "codePostal": "33420",
    "population": 2041,
    "latitude": 44.8614,
    "longitude": -0.2496,
    "altitude": 69,
    "logements": 928,
    "logementsMaison": 87,
    "prixM2Moyen": 3490,
    "vehiculesElectriques": 101,
    "croissanceVE": 18,
    "bornesPubliques": 6,
    "intercommunalite": "Communauté de Communes des Portes de l'Entre-deux-Mers",
    "canton": "Génissac",
    "distanceBordeaux": 26.1,
    "densiteBornes": 2.9,
    "profilCommune": "bourg périurbain",
    "marcheImmobilier": "intermédiaire",
    "tauxMaisonLabel": "très pavillonnaire"
  }
]
